final class bx extends Thread {
  private final String a;
  
  final eb a;
  
  bx(eb parameb, String paramString) {
    this.a = parameb;
    this.a = (eb)paramString;
  }
  
  public final void run() {
    // Byte code:
    //   0: aload_0
    //   1: getfield a : Ljava/lang/String;
    //   4: invokestatic a : (Ljava/lang/String;)Z
    //   7: ifeq -> 256
    //   10: aload_0
    //   11: getfield a : Ljava/lang/String;
    //   14: iconst_1
    //   15: invokestatic open : (Ljava/lang/String;I)Ljavax/microedition/io/Connection;
    //   18: checkcast javax/microedition/io/file/FileConnection
    //   21: astore_1
    //   22: aload_0
    //   23: getfield a : Leb;
    //   26: getfield a : I
    //   29: aload_1
    //   30: invokeinterface usedSize : ()J
    //   35: aload_1
    //   36: invokeinterface getName : ()Ljava/lang/String;
    //   41: aload_1
    //   42: invokeinterface openInputStream : ()Ljava/io/InputStream;
    //   47: astore #6
    //   49: astore_3
    //   50: lstore #4
    //   52: istore_2
    //   53: new ju
    //   56: dup
    //   57: iload_2
    //   58: invokespecial <init> : (I)V
    //   61: aconst_null
    //   62: invokevirtual a : (Liq;)Laj;
    //   65: checkcast fi
    //   68: dup
    //   69: astore_2
    //   70: ifnull -> 157
    //   73: aload_2
    //   74: getfield a : Ljava/lang/String;
    //   77: invokestatic a : (Ljava/lang/String;)Z
    //   80: ifne -> 87
    //   83: iconst_1
    //   84: goto -> 88
    //   87: iconst_0
    //   88: ifeq -> 157
    //   91: aload_2
    //   92: getfield a : Ljava/lang/String;
    //   95: lload #4
    //   97: aload_3
    //   98: aload #6
    //   100: invokestatic a : (Ljava/lang/String;JLjava/lang/String;Ljava/io/InputStream;)Ljava/lang/String;
    //   103: astore_2
    //   104: new bj
    //   107: dup
    //   108: aload_2
    //   109: invokespecial <init> : (Ljava/lang/String;)V
    //   112: astore_2
    //   113: new cf
    //   116: dup
    //   117: aload_2
    //   118: ldc 'photo'
    //   120: invokevirtual a : (Ljava/lang/String;)Ljava/lang/String;
    //   123: aload_2
    //   124: ldc 'server'
    //   126: invokevirtual a : (Ljava/lang/String;)J
    //   129: aload_2
    //   130: ldc 'hash'
    //   132: invokevirtual a : (Ljava/lang/String;)Ljava/lang/String;
    //   135: invokespecial <init> : (Ljava/lang/String;JLjava/lang/String;)V
    //   138: aconst_null
    //   139: invokevirtual a : (Liq;)Laj;
    //   142: checkcast hl
    //   145: dup
    //   146: astore_2
    //   147: ifnull -> 157
    //   150: aload_2
    //   151: getfield a : Ljc;
    //   154: goto -> 158
    //   157: aconst_null
    //   158: dup
    //   159: astore_2
    //   160: ifnull -> 174
    //   163: aload_0
    //   164: getfield a : Leb;
    //   167: getfield b : Ljava/util/Vector;
    //   170: aload_2
    //   171: invokevirtual addElement : (Ljava/lang/Object;)V
    //   174: aload_1
    //   175: invokeinterface close : ()V
    //   180: aload_0
    //   181: getfield a : Leb;
    //   184: invokestatic a : (Leb;)V
    //   187: return
    //   188: astore_1
    //   189: new la
    //   192: dup
    //   193: invokespecial <init> : ()V
    //   196: iconst_1
    //   197: invokevirtual a : (Z)Lla;
    //   200: dup
    //   201: astore_2
    //   202: ldc 'action.back'
    //   204: invokestatic a : (Ljava/lang/String;)Ljava/lang/String;
    //   207: new db
    //   210: dup
    //   211: aload_0
    //   212: invokespecial <init> : (Lbx;)V
    //   215: iconst_0
    //   216: invokestatic a : (Lla;Ljava/lang/String;Ljava/lang/Runnable;Z)V
    //   219: aload_2
    //   220: getfield b : Ljava/util/Vector;
    //   223: new gg
    //   226: dup
    //   227: aload_1
    //   228: invokevirtual toString : ()Ljava/lang/String;
    //   231: invokespecial <init> : (Ljava/lang/String;)V
    //   234: invokevirtual addElement : (Ljava/lang/Object;)V
    //   237: getstatic gz.a : Lgz;
    //   240: aload_2
    //   241: invokevirtual b : (Lla;)V
    //   244: return
    //   245: pop
    //   246: invokestatic gc : ()V
    //   249: aload_0
    //   250: getfield a : Leb;
    //   253: invokestatic a : (Leb;)V
    //   256: return
    // Exception table:
    //   from	to	target	type
    //   10	187	188	java/lang/Exception
    //   10	187	245	java/lang/OutOfMemoryError
  }
}


/* Location:              /home/kost/Загрузки/latest.jar!/bx.class
 * Java compiler version: 4 (48.0)
 * JD-Core Version:       1.1.3
 */