final class cb extends Thread {
  private final boolean a;
  
  private final cm a;
  
  private final ea a;
  
  cb(ea paramea, boolean paramBoolean, cm paramcm) {
    this.a = paramea;
    this.a = paramBoolean;
    this.a = (ea)paramcm;
  }
  
  public final void run() {
    // Byte code:
    //   0: aload_0
    //   1: getfield a : Lea;
    //   4: getfield a : Ljp;
    //   7: invokevirtual a : ()Z
    //   10: ifne -> 20
    //   13: aload_0
    //   14: getfield a : Z
    //   17: ifeq -> 31
    //   20: aload_0
    //   21: getfield a : Lea;
    //   24: aload_0
    //   25: getfield a : Lcm;
    //   28: invokevirtual a : (Lcm;)V
    //   31: invokestatic d : ()V
    //   34: aload_0
    //   35: getfield a : Lea;
    //   38: getfield a : Ljp;
    //   41: dup
    //   42: astore_1
    //   43: getfield a : Ljavax/microedition/media/Player;
    //   46: ifnull -> 123
    //   49: aload_1
    //   50: getfield b : I
    //   53: iconst_m1
    //   54: if_icmpeq -> 72
    //   57: aload_1
    //   58: getfield a : Ljavax/microedition/media/Player;
    //   61: aload_1
    //   62: getfield b : I
    //   65: i2l
    //   66: invokeinterface setMediaTime : (J)J
    //   71: pop2
    //   72: aload_1
    //   73: aload_1
    //   74: getfield a : I
    //   77: invokevirtual a : (I)V
    //   80: aload_1
    //   81: getfield a : Ljavax/microedition/media/Player;
    //   84: invokeinterface start : ()V
    //   89: aload_1
    //   90: getfield b : I
    //   93: iconst_m1
    //   94: if_icmpeq -> 112
    //   97: aload_1
    //   98: getfield a : Ljavax/microedition/media/Player;
    //   101: aload_1
    //   102: getfield b : I
    //   105: i2l
    //   106: invokeinterface setMediaTime : (J)J
    //   111: pop2
    //   112: aload_1
    //   113: iconst_m1
    //   114: putfield b : I
    //   117: return
    //   118: pop
    //   119: aload_1
    //   120: invokevirtual a : ()V
    //   123: return
    // Exception table:
    //   from	to	target	type
    //   49	117	118	javax/microedition/media/MediaException
  }
}


/* Location:              /home/kost/Загрузки/latest.jar!/cb.class
 * Java compiler version: 4 (48.0)
 * JD-Core Version:       1.1.3
 */