final class ce extends Thread {
  final cm a;
  
  final ea a;
  
  ce(ea paramea, cm paramcm) {
    this.a = paramea;
    this.a = (ea)paramcm;
  }
  
  public final void run() {
    // Byte code:
    //   0: aload_0
    //   1: getfield a : Lea;
    //   4: iconst_1
    //   5: putfield b : Z
    //   8: aload_0
    //   9: getfield a : Lea;
    //   12: iconst_1
    //   13: putfield c : Z
    //   16: aload_0
    //   17: getfield a : Lcm;
    //   20: invokestatic a : (Lcm;)Ljava/lang/String;
    //   23: iconst_3
    //   24: invokestatic open : (Ljava/lang/String;I)Ljavax/microedition/io/Connection;
    //   27: checkcast javax/microedition/io/file/FileConnection
    //   30: dup
    //   31: astore_1
    //   32: invokeinterface exists : ()Z
    //   37: ifne -> 46
    //   40: aload_1
    //   41: invokeinterface create : ()V
    //   46: aload_1
    //   47: invokeinterface canWrite : ()Z
    //   52: ifeq -> 84
    //   55: new dz
    //   58: dup
    //   59: aload_0
    //   60: invokespecial <init> : (Lce;)V
    //   63: astore_2
    //   64: aload_0
    //   65: getfield a : Lcm;
    //   68: getfield a : Ljava/lang/String;
    //   71: aload_1
    //   72: invokeinterface openOutputStream : ()Ljava/io/OutputStream;
    //   77: aload_2
    //   78: invokestatic a : (Ljava/lang/String;Ljava/io/OutputStream;Lca;)V
    //   81: goto -> 94
    //   84: new java/io/IOException
    //   87: dup
    //   88: ldc 'Can't write a file.'
    //   90: invokespecial <init> : (Ljava/lang/String;)V
    //   93: athrow
    //   94: aload_1
    //   95: invokeinterface close : ()V
    //   100: goto -> 146
    //   103: astore_1
    //   104: getstatic ci.a : Lv;
    //   107: iconst_0
    //   108: putfield m : Z
    //   111: getstatic ci.a : Lv;
    //   114: invokevirtual a : ()Lv;
    //   117: pop
    //   118: getstatic gz.a : Lgz;
    //   121: new java/lang/StringBuffer
    //   124: dup
    //   125: invokespecial <init> : ()V
    //   128: ldc 'Caching error: '
    //   130: invokevirtual append : (Ljava/lang/String;)Ljava/lang/StringBuffer;
    //   133: aload_1
    //   134: invokevirtual toString : ()Ljava/lang/String;
    //   137: invokevirtual append : (Ljava/lang/String;)Ljava/lang/StringBuffer;
    //   140: invokevirtual toString : ()Ljava/lang/String;
    //   143: invokevirtual a : (Ljava/lang/String;)V
    //   146: aload_0
    //   147: getfield a : Lea;
    //   150: iconst_0
    //   151: putfield c : Z
    //   154: aload_0
    //   155: getfield a : Lcm;
    //   158: invokestatic a : (Lcm;)Z
    //   161: ifeq -> 231
    //   164: aload_0
    //   165: getfield a : Lea;
    //   168: aload_0
    //   169: getfield a : Lcm;
    //   172: invokestatic a : (Lcm;)Ljava/lang/String;
    //   175: iconst_1
    //   176: invokestatic open : (Ljava/lang/String;I)Ljavax/microedition/io/Connection;
    //   179: checkcast javax/microedition/io/file/FileConnection
    //   182: putfield a : Ljavax/microedition/io/file/FileConnection;
    //   185: aload_0
    //   186: getfield a : Lea;
    //   189: getfield a : Ljp;
    //   192: aload_0
    //   193: getfield a : Lea;
    //   196: getfield a : Ljavax/microedition/io/file/FileConnection;
    //   199: invokeinterface openInputStream : ()Ljava/io/InputStream;
    //   204: invokevirtual a : (Ljava/io/InputStream;)V
    //   207: goto -> 231
    //   210: pop
    //   211: aload_0
    //   212: getfield a : Lea;
    //   215: getfield a : Ljp;
    //   218: aload_0
    //   219: getfield a : Lcm;
    //   222: getfield a : Ljava/lang/String;
    //   225: invokestatic a : (Ljava/lang/String;)Ljava/io/InputStream;
    //   228: invokevirtual a : (Ljava/io/InputStream;)V
    //   231: aload_0
    //   232: getfield a : Lea;
    //   235: iconst_0
    //   236: putfield b : Z
    //   239: return
    // Exception table:
    //   from	to	target	type
    //   16	100	103	java/lang/Exception
    //   164	207	210	java/lang/Exception
  }
}


/* Location:              /home/kost/Загрузки/latest.jar!/ce.class
 * Java compiler version: 4 (48.0)
 * JD-Core Version:       1.1.3
 */