final class dx extends Thread {
  private final String a;
  
  private final String b;
  
  private final boolean a;
  
  dx(String paramString1, String paramString2, boolean paramBoolean) {
    this.a = paramString1;
    this.b = paramString2;
    this.a = paramBoolean;
  }
  
  public final void run() {
    // Byte code:
    //   0: getstatic fw.a : Lar;
    //   3: ifnull -> 15
    //   6: getstatic fw.a : Lar;
    //   9: getfield a : Ljava/lang/String;
    //   12: goto -> 16
    //   15: aconst_null
    //   16: getstatic fw.a : Laz;
    //   19: ifnull -> 31
    //   22: getstatic fw.a : Laz;
    //   25: getfield a : Ljava/lang/String;
    //   28: goto -> 32
    //   31: aconst_null
    //   32: aload_0
    //   33: getfield a : Ljava/lang/String;
    //   36: aload_0
    //   37: getfield b : Ljava/lang/String;
    //   40: getstatic fw.b : Lar;
    //   43: ifnull -> 55
    //   46: getstatic fw.b : Lar;
    //   49: getfield a : Ljava/lang/String;
    //   52: goto -> 56
    //   55: aconst_null
    //   56: aload_0
    //   57: getfield a : Z
    //   60: invokestatic a : (Ljava/lang/String;Ljava/lang/String;Ljava/lang/String;Ljava/lang/String;Ljava/lang/String;Z)Lkl;
    //   63: dup
    //   64: astore_1
    //   65: getfield a : I
    //   68: tableswitch default -> 473, -2 -> 324, -1 -> 324, 0 -> 160, 1 -> 177, 2 -> 324, 3 -> 143, 4 -> 112
    //   112: getstatic fw.a : Lr;
    //   115: ifnull -> 137
    //   118: getstatic fw.a : Lr;
    //   121: getfield e : Z
    //   124: ifeq -> 137
    //   127: getstatic fy.a : Liq;
    //   130: getfield a : Ljava/lang/String;
    //   133: invokestatic a : (Ljava/lang/String;)Ljava/lang/String;
    //   136: pop
    //   137: invokestatic e : ()V
    //   140: goto -> 487
    //   143: invokestatic a : ()V
    //   146: getstatic gz.a : Lgz;
    //   149: ldc 'auth.invalidPair'
    //   151: invokestatic a : (Ljava/lang/String;)Ljava/lang/String;
    //   154: invokevirtual a : (Ljava/lang/String;)V
    //   157: goto -> 487
    //   160: invokestatic a : ()V
    //   163: getstatic gz.a : Lgz;
    //   166: ldc 'auth.unknownError'
    //   168: invokestatic a : (Ljava/lang/String;)Ljava/lang/String;
    //   171: invokevirtual a : (Ljava/lang/String;)V
    //   174: goto -> 487
    //   177: aload_1
    //   178: getfield a : Lae;
    //   181: getfield c : Ljava/lang/String;
    //   184: aload_1
    //   185: getfield a : Lae;
    //   188: getfield b : Ljava/lang/String;
    //   191: astore_1
    //   192: astore_2
    //   193: invokestatic d : ()V
    //   196: getstatic fw.a : Lgz;
    //   199: iconst_1
    //   200: putfield d : Z
    //   203: new la
    //   206: dup
    //   207: invokespecial <init> : ()V
    //   210: dup
    //   211: astore_3
    //   212: iconst_1
    //   213: putfield d : Z
    //   216: aload_3
    //   217: ldc 'title.CAPTCHA'
    //   219: invokestatic a : (Ljava/lang/String;)Ljava/lang/String;
    //   222: invokevirtual c : (Ljava/lang/String;)V
    //   225: new ar
    //   228: dup
    //   229: ldc 'element.CAPTCHACode'
    //   231: invokestatic a : (Ljava/lang/String;)Ljava/lang/String;
    //   234: invokespecial <init> : (Ljava/lang/String;)V
    //   237: astore #4
    //   239: aload_3
    //   240: getfield b : Ljava/util/Vector;
    //   243: new fl
    //   246: dup
    //   247: aload_2
    //   248: invokestatic b : (Ljava/lang/String;)Ljavax/microedition/lcdui/Image;
    //   251: invokespecial <init> : (Ljavax/microedition/lcdui/Image;)V
    //   254: dup
    //   255: astore_2
    //   256: iconst_1
    //   257: putfield a : B
    //   260: aload_2
    //   261: invokevirtual addElement : (Ljava/lang/Object;)V
    //   264: aload_3
    //   265: getfield b : Ljava/util/Vector;
    //   268: aload #4
    //   270: invokevirtual addElement : (Ljava/lang/Object;)V
    //   273: aload_3
    //   274: getfield b : Ljava/util/Vector;
    //   277: new du
    //   280: dup
    //   281: ldc 'action.confirm'
    //   283: invokestatic a : (Ljava/lang/String;)Ljava/lang/String;
    //   286: aload #4
    //   288: aload_1
    //   289: invokespecial <init> : (Ljava/lang/String;Lar;Ljava/lang/String;)V
    //   292: invokevirtual addElement : (Ljava/lang/Object;)V
    //   295: aload_3
    //   296: getfield b : Ljava/util/Vector;
    //   299: new dh
    //   302: dup
    //   303: ldc 'action.cancel'
    //   305: invokestatic a : (Ljava/lang/String;)Ljava/lang/String;
    //   308: invokespecial <init> : (Ljava/lang/String;)V
    //   311: invokevirtual addElement : (Ljava/lang/Object;)V
    //   314: getstatic fw.a : Lgz;
    //   317: aload_3
    //   318: invokevirtual b : (Lla;)V
    //   321: goto -> 487
    //   324: invokestatic d : ()V
    //   327: getstatic fw.a : Lgz;
    //   330: iconst_1
    //   331: putfield d : Z
    //   334: getstatic fw.a : Lla;
    //   337: ifnonnull -> 457
    //   340: new la
    //   343: dup
    //   344: invokespecial <init> : ()V
    //   347: dup
    //   348: putstatic fw.a : Lla;
    //   351: iconst_1
    //   352: putfield d : Z
    //   355: getstatic fw.a : Lla;
    //   358: ldc 'title.2FA'
    //   360: invokestatic a : (Ljava/lang/String;)Ljava/lang/String;
    //   363: invokevirtual c : (Ljava/lang/String;)V
    //   366: getstatic fw.a : Lla;
    //   369: getfield b : Ljava/util/Vector;
    //   372: new ar
    //   375: dup
    //   376: ldc 'element.2FACode'
    //   378: invokestatic a : (Ljava/lang/String;)Ljava/lang/String;
    //   381: invokespecial <init> : (Ljava/lang/String;)V
    //   384: dup
    //   385: putstatic fw.b : Lar;
    //   388: invokevirtual addElement : (Ljava/lang/Object;)V
    //   391: getstatic fw.a : Lla;
    //   394: getfield b : Ljava/util/Vector;
    //   397: new dg
    //   400: dup
    //   401: ldc 'action.confirm'
    //   403: invokestatic a : (Ljava/lang/String;)Ljava/lang/String;
    //   406: invokespecial <init> : (Ljava/lang/String;)V
    //   409: invokevirtual addElement : (Ljava/lang/Object;)V
    //   412: getstatic fw.a : Lla;
    //   415: getfield b : Ljava/util/Vector;
    //   418: new dk
    //   421: dup
    //   422: ldc 'action.sendSMS'
    //   424: invokestatic a : (Ljava/lang/String;)Ljava/lang/String;
    //   427: invokespecial <init> : (Ljava/lang/String;)V
    //   430: invokevirtual addElement : (Ljava/lang/Object;)V
    //   433: getstatic fw.a : Lla;
    //   436: getfield b : Ljava/util/Vector;
    //   439: new di
    //   442: dup
    //   443: ldc 'action.cancel'
    //   445: invokestatic a : (Ljava/lang/String;)Ljava/lang/String;
    //   448: invokespecial <init> : (Ljava/lang/String;)V
    //   451: invokevirtual addElement : (Ljava/lang/Object;)V
    //   454: goto -> 464
    //   457: getstatic fw.b : Lar;
    //   460: aconst_null
    //   461: invokevirtual b : (Ljava/lang/String;)V
    //   464: getstatic fw.a : Lgz;
    //   467: getstatic fw.a : Lla;
    //   470: invokevirtual b : (Lla;)V
    //   473: goto -> 487
    //   476: astore_1
    //   477: invokestatic a : ()V
    //   480: getstatic gz.a : Lgz;
    //   483: aload_1
    //   484: invokevirtual a : (Ljava/lang/Exception;)V
    //   487: getstatic fw.a : Lgz;
    //   490: iconst_0
    //   491: invokevirtual b : (Z)V
    //   494: return
    // Exception table:
    //   from	to	target	type
    //   0	473	476	java/lang/Exception
  }
}


/* Location:              /home/kost/Загрузки/latest.jar!/dx.class
 * Java compiler version: 4 (48.0)
 * JD-Core Version:       1.1.3
 */