public final class e extends la {
  final dm a;
  
  private e(dm paramdm, byte paramByte) {
    // Byte code:
    //   0: aload_0
    //   1: ldc 'title.networkMode'
    //   3: invokestatic a : (Ljava/lang/String;)Ljava/lang/String;
    //   6: invokespecial <init> : (Ljava/lang/String;)V
    //   9: aload_0
    //   10: aload_1
    //   11: putfield a : Ldm;
    //   14: aload_0
    //   15: iconst_1
    //   16: invokevirtual a : (Z)Lla;
    //   19: pop
    //   20: aload_0
    //   21: ldc 'action.back'
    //   23: invokestatic a : (Ljava/lang/String;)Ljava/lang/String;
    //   26: new ex
    //   29: dup
    //   30: aload_0
    //   31: invokespecial <init> : (Le;)V
    //   34: iconst_1
    //   35: invokestatic a : (Lla;Ljava/lang/String;Ljava/lang/Runnable;Z)V
    //   38: aload_0
    //   39: getfield b : Ljava/util/Vector;
    //   42: new ak
    //   45: dup
    //   46: invokespecial <init> : ()V
    //   49: invokevirtual addElement : (Ljava/lang/Object;)V
    //   52: aload_0
    //   53: getfield b : Ljava/util/Vector;
    //   56: new et
    //   59: dup
    //   60: aload_0
    //   61: ldc 'settings.httpByXtrafrancyzMode'
    //   63: invokestatic a : (Ljava/lang/String;)Ljava/lang/String;
    //   66: invokespecial <init> : (Le;Ljava/lang/String;)V
    //   69: getstatic ci.a : Lv;
    //   72: getfield b : I
    //   75: ifne -> 82
    //   78: iconst_1
    //   79: goto -> 83
    //   82: iconst_0
    //   83: invokevirtual b : (Z)Lr;
    //   86: dup
    //   87: astore_2
    //   88: iconst_1
    //   89: putfield o : Z
    //   92: aload_2
    //   93: dup
    //   94: astore_2
    //   95: iconst_1
    //   96: putfield n : Z
    //   99: aload_2
    //   100: invokevirtual addElement : (Ljava/lang/Object;)V
    //   103: aload_0
    //   104: getfield b : Ljava/util/Vector;
    //   107: new ep
    //   110: dup
    //   111: aload_0
    //   112: ldc 'settings.httpsByVKMode'
    //   114: invokestatic a : (Ljava/lang/String;)Ljava/lang/String;
    //   117: invokespecial <init> : (Le;Ljava/lang/String;)V
    //   120: getstatic ci.a : Lv;
    //   123: getfield b : I
    //   126: iconst_1
    //   127: if_icmpne -> 134
    //   130: iconst_1
    //   131: goto -> 135
    //   134: iconst_0
    //   135: invokevirtual b : (Z)Lr;
    //   138: invokevirtual addElement : (Ljava/lang/Object;)V
    //   141: invokestatic b : ()Z
    //   144: ifne -> 157
    //   147: new java/lang/IllegalStateException
    //   150: dup
    //   151: ldc 'No HTTPS.'
    //   153: invokespecial <init> : (Ljava/lang/String;)V
    //   156: athrow
    //   157: goto -> 196
    //   160: pop
    //   161: aload_0
    //   162: getfield b : Ljava/util/Vector;
    //   165: new gg
    //   168: dup
    //   169: ldc 'settings.httpsNotSupportedDisclaimer'
    //   171: invokestatic a : (Ljava/lang/String;)Ljava/lang/String;
    //   174: invokespecial <init> : (Ljava/lang/String;)V
    //   177: iconst_1
    //   178: invokevirtual b : (I)Lgg;
    //   181: ldc 6579300
    //   183: invokevirtual a : (I)Lgg;
    //   186: dup
    //   187: astore_2
    //   188: iconst_1
    //   189: putfield r : Z
    //   192: aload_2
    //   193: invokevirtual addElement : (Ljava/lang/Object;)V
    //   196: aload_0
    //   197: astore_1
    //   198: getstatic gz.a : Lgz;
    //   201: aload_1
    //   202: invokevirtual b : (Lla;)V
    //   205: return
    // Exception table:
    //   from	to	target	type
    //   141	157	160	java/lang/Throwable
  }
  
  e(dm paramdm) {
    this(paramdm, (byte)0);
  }
}


/* Location:              /home/kost/Загрузки/latest.jar!/e.class
 * Java compiler version: 4 (48.0)
 * JD-Core Version:       1.1.3
 */