final class eq extends r {
  private final bw a;
  
  private final eb a;
  
  eq(eb parameb, String paramString, bw parambw) {
    super(paramString);
    this.a = parameb;
    this.a = (eb)parambw;
  }
  
  public final void a() {
    // Byte code:
    //   0: aload_0
    //   1: getfield a : Leb;
    //   4: getfield a : Ljava/util/Vector;
    //   7: aload_0
    //   8: getfield a : Lbw;
    //   11: invokevirtual removeElement : (Ljava/lang/Object;)Z
    //   14: pop
    //   15: aload_0
    //   16: getfield a : Leb;
    //   19: getfield a : Lla;
    //   22: getfield b : Ljava/util/Vector;
    //   25: aload_0
    //   26: invokevirtual removeElement : (Ljava/lang/Object;)Z
    //   29: pop
    //   30: return
  }
}


/* Location:              /home/kost/Загрузки/latest.jar!/eq.class
 * Java compiler version: 4 (48.0)
 * JD-Core Version:       1.1.3
 */