import java.util.Vector;

public final class i extends jr {
  private boolean c;
  
  private static Thread a;
  
  private Vector a;
  
  private static i a;
  
  lb a;
  
  private int a;
  
  public i(int paramInt) {
    // Byte code:
    //   0: aload_0
    //   1: invokespecial <init> : ()V
    //   4: aload_0
    //   5: new java/util/Vector
    //   8: dup
    //   9: invokespecial <init> : ()V
    //   12: putfield a : Ljava/util/Vector;
    //   15: aload_0
    //   16: iconst_0
    //   17: putfield a : I
    //   20: aload_0
    //   21: iconst_1
    //   22: putfield b : Z
    //   25: aload_0
    //   26: putstatic i.a : Li;
    //   29: aload_0
    //   30: iload_1
    //   31: iconst_1
    //   32: invokestatic a : (IZ)Llb;
    //   35: putfield a : Llb;
    //   38: aload_0
    //   39: new java/lang/StringBuffer
    //   42: dup
    //   43: invokespecial <init> : ()V
    //   46: ldc '@'
    //   48: invokevirtual append : (Ljava/lang/String;)Ljava/lang/StringBuffer;
    //   51: aload_0
    //   52: getfield a : Llb;
    //   55: invokevirtual d : ()Ljava/lang/String;
    //   58: invokevirtual append : (Ljava/lang/String;)Ljava/lang/StringBuffer;
    //   61: invokevirtual toString : ()Ljava/lang/String;
    //   64: invokevirtual c : (Ljava/lang/String;)V
    //   67: new ek
    //   70: dup
    //   71: aload_0
    //   72: invokespecial <init> : (Li;)V
    //   75: invokevirtual start : ()V
    //   78: return
  }
  
  public final void a() {
    // Byte code:
    //   0: aload_0
    //   1: getfield a : Z
    //   4: ifne -> 14
    //   7: aload_0
    //   8: getfield c : Z
    //   11: ifne -> 15
    //   14: return
    //   15: aload_0
    //   16: dup
    //   17: astore_1
    //   18: getfield a : I
    //   21: istore_2
    //   22: iload_2
    //   23: aload_1
    //   24: getfield b : Ljava/util/Vector;
    //   27: invokevirtual size : ()I
    //   30: if_icmpge -> 44
    //   33: aload_1
    //   34: getfield b : Ljava/util/Vector;
    //   37: iload_2
    //   38: invokevirtual removeElementAt : (I)V
    //   41: goto -> 22
    //   44: aload_0
    //   45: aconst_null
    //   46: putfield a : Ljava/lang/Object;
    //   49: aload_0
    //   50: aconst_null
    //   51: putfield b : Ljava/lang/Object;
    //   54: aload_0
    //   55: iconst_0
    //   56: putfield b : Z
    //   59: return
  }
  
  private void b(ay paramay) {
    // Byte code:
    //   0: aload_0
    //   1: getfield b : Ljava/util/Vector;
    //   4: aload_1
    //   5: invokevirtual addElement : (Ljava/lang/Object;)V
    //   8: aload_0
    //   9: dup
    //   10: getfield a : I
    //   13: iconst_1
    //   14: iadd
    //   15: putfield a : I
    //   18: return
  }
  
  public final void b() {
    if (this.a != 0 || !this.c)
      return; 
    a();
    g();
  }
  
  public final void c() {
    // Byte code:
    //   0: aload_0
    //   1: getfield c : Z
    //   4: ifne -> 8
    //   7: return
    //   8: getstatic gz.a : Lgz;
    //   11: iconst_1
    //   12: invokevirtual b : (Z)V
    //   15: aload_0
    //   16: getfield a : Ljava/lang/Object;
    //   19: ifnonnull -> 26
    //   22: iconst_1
    //   23: goto -> 27
    //   26: iconst_0
    //   27: ifeq -> 42
    //   30: aload_0
    //   31: new java/lang/Integer
    //   34: dup
    //   35: iconst_m1
    //   36: invokespecial <init> : (I)V
    //   39: putfield a : Ljava/lang/Object;
    //   42: aload_0
    //   43: new java/lang/Integer
    //   46: dup
    //   47: aload_0
    //   48: getfield a : Ljava/lang/Object;
    //   51: checkcast java/lang/Integer
    //   54: invokevirtual intValue : ()I
    //   57: iconst_1
    //   58: iadd
    //   59: invokespecial <init> : (I)V
    //   62: putfield a : Ljava/lang/Object;
    //   65: new java/util/Vector
    //   68: dup
    //   69: invokespecial <init> : ()V
    //   72: astore_1
    //   73: new ch
    //   76: dup
    //   77: aload_0
    //   78: getfield a : Llb;
    //   81: invokevirtual a : ()I
    //   84: aload_0
    //   85: getfield a : Ljava/lang/Object;
    //   88: checkcast java/lang/Integer
    //   91: invokevirtual intValue : ()I
    //   94: bipush #20
    //   96: imul
    //   97: invokespecial <init> : (II)V
    //   100: invokevirtual a : ()Laj;
    //   103: checkcast he
    //   106: dup
    //   107: astore_2
    //   108: ifnull -> 228
    //   111: aload_2
    //   112: dup
    //   113: astore_3
    //   114: getfield a : [Laa;
    //   117: ifnull -> 132
    //   120: aload_3
    //   121: getfield a : [Laa;
    //   124: arraylength
    //   125: ifle -> 132
    //   128: iconst_1
    //   129: goto -> 133
    //   132: iconst_0
    //   133: ifeq -> 228
    //   136: aload_2
    //   137: getfield a : [Laa;
    //   140: arraylength
    //   141: bipush #20
    //   143: if_icmpge -> 151
    //   146: aload_0
    //   147: iconst_1
    //   148: putfield b : Z
    //   151: iconst_0
    //   152: istore_3
    //   153: iload_3
    //   154: aload_2
    //   155: getfield a : [Laa;
    //   158: arraylength
    //   159: if_icmpge -> 214
    //   162: aload_0
    //   163: aload_2
    //   164: getfield a : [Laa;
    //   167: iload_3
    //   168: aaload
    //   169: invokespecial a : (Laa;)[Lr;
    //   172: astore #4
    //   174: iconst_0
    //   175: istore #5
    //   177: iload #5
    //   179: aload #4
    //   181: arraylength
    //   182: if_icmpge -> 208
    //   185: aload #4
    //   187: iload #5
    //   189: aaload
    //   190: dup
    //   191: astore #6
    //   193: ifnull -> 202
    //   196: aload_1
    //   197: aload #6
    //   199: invokevirtual addElement : (Ljava/lang/Object;)V
    //   202: iinc #5, 1
    //   205: goto -> 177
    //   208: iinc #3, 1
    //   211: goto -> 153
    //   214: new ei
    //   217: dup
    //   218: aload_1
    //   219: invokespecial <init> : (Ljava/util/Vector;)V
    //   222: invokevirtual start : ()V
    //   225: goto -> 248
    //   228: aload_0
    //   229: iconst_1
    //   230: putfield b : Z
    //   233: aload_2
    //   234: ifnonnull -> 248
    //   237: getstatic gz.a : Lgz;
    //   240: ldc 'general.loadError'
    //   242: invokestatic a : (Ljava/lang/String;)Ljava/lang/String;
    //   245: invokevirtual a : (Ljava/lang/String;)V
    //   248: getstatic gz.a : Lgz;
    //   251: iconst_0
    //   252: invokevirtual b : (Z)V
    //   255: return
  }
  
  private r[] a(aa paramaa) {
    // Byte code:
    //   0: aload_1
    //   1: ifnonnull -> 9
    //   4: iconst_0
    //   5: anewarray r
    //   8: areturn
    //   9: aload_0
    //   10: getfield b : Ljava/util/Vector;
    //   13: invokevirtual size : ()I
    //   16: iconst_1
    //   17: if_icmpne -> 34
    //   20: aload_0
    //   21: getfield b : Ljava/util/Vector;
    //   24: new ak
    //   27: dup
    //   28: invokespecial <init> : ()V
    //   31: invokevirtual addElement : (Ljava/lang/Object;)V
    //   34: iconst_4
    //   35: anewarray r
    //   38: astore_2
    //   39: aload_0
    //   40: getfield b : Ljava/util/Vector;
    //   43: aload_2
    //   44: iconst_0
    //   45: aload_1
    //   46: getfield a : I
    //   49: invokestatic a : (I)Llb;
    //   52: iconst_0
    //   53: iconst_1
    //   54: iconst_1
    //   55: iconst_0
    //   56: iconst_1
    //   57: invokestatic a : (Llb;ZZZZZ)Lr;
    //   60: aload_1
    //   61: getfield b : I
    //   64: invokestatic c : (I)Ljava/lang/String;
    //   67: invokevirtual c : (Ljava/lang/String;)Lr;
    //   70: aload_1
    //   71: invokevirtual d : ()Z
    //   74: ifne -> 98
    //   77: aload_1
    //   78: invokevirtual c : ()Z
    //   81: ifne -> 102
    //   84: aload_1
    //   85: invokevirtual b : ()Z
    //   88: ifne -> 102
    //   91: aload_1
    //   92: invokevirtual a : ()Z
    //   95: ifeq -> 102
    //   98: iconst_1
    //   99: goto -> 103
    //   102: iconst_0
    //   103: istore #6
    //   105: dup
    //   106: astore #5
    //   108: iload #6
    //   110: putfield n : Z
    //   113: aload #5
    //   115: checkcast r
    //   118: dup_x2
    //   119: aastore
    //   120: invokevirtual addElement : (Ljava/lang/Object;)V
    //   123: aload_1
    //   124: invokevirtual d : ()Z
    //   127: ifeq -> 187
    //   130: aload_1
    //   131: getfield c : I
    //   134: aload_1
    //   135: getfield a : I
    //   138: if_icmpeq -> 187
    //   141: aload_0
    //   142: getfield b : Ljava/util/Vector;
    //   145: aload_2
    //   146: iconst_1
    //   147: aload_1
    //   148: getfield c : I
    //   151: invokestatic a : (I)Llb;
    //   154: iconst_1
    //   155: iconst_1
    //   156: iconst_1
    //   157: iconst_0
    //   158: iconst_1
    //   159: invokestatic a : (Llb;ZZZZZ)Lr;
    //   162: ldc 'general.author'
    //   164: invokestatic a : (Ljava/lang/String;)Ljava/lang/String;
    //   167: invokevirtual b : (Ljava/lang/String;)Lr;
    //   170: dup
    //   171: astore #5
    //   173: iconst_0
    //   174: putfield n : Z
    //   177: aload #5
    //   179: checkcast r
    //   182: dup_x2
    //   183: aastore
    //   184: invokevirtual addElement : (Ljava/lang/Object;)V
    //   187: aload_1
    //   188: invokevirtual c : ()Z
    //   191: ifeq -> 212
    //   194: aload_0
    //   195: getfield b : Ljava/util/Vector;
    //   198: new gg
    //   201: dup
    //   202: aload_1
    //   203: getfield a : Ljava/lang/String;
    //   206: invokespecial <init> : (Ljava/lang/String;)V
    //   209: invokevirtual addElement : (Ljava/lang/Object;)V
    //   212: aload_1
    //   213: invokevirtual b : ()Z
    //   216: ifeq -> 445
    //   219: iconst_0
    //   220: istore_3
    //   221: iload_3
    //   222: aload_1
    //   223: getfield a : [Ldv;
    //   226: arraylength
    //   227: if_icmpge -> 445
    //   230: aload_1
    //   231: getfield a : [Ldv;
    //   234: iload_3
    //   235: aaload
    //   236: dup
    //   237: astore #4
    //   239: ifnull -> 439
    //   242: aload #4
    //   244: instanceof jc
    //   247: ifeq -> 334
    //   250: aload #4
    //   252: checkcast jc
    //   255: invokevirtual a : ()Leh;
    //   258: astore #5
    //   260: aload_0
    //   261: getfield b : Ljava/util/Vector;
    //   264: new fl
    //   267: dup
    //   268: invokespecial <init> : ()V
    //   271: aload #5
    //   273: getfield a : I
    //   276: aload #5
    //   278: getfield b : I
    //   281: invokevirtual a : (II)Lfl;
    //   284: aload #4
    //   286: astore #6
    //   288: dup
    //   289: astore #5
    //   291: aload #6
    //   293: putfield a : Lad;
    //   296: aload #5
    //   298: dup
    //   299: astore #5
    //   301: iconst_1
    //   302: putfield a : B
    //   305: aload #5
    //   307: dup
    //   308: astore #5
    //   310: iconst_1
    //   311: putfield a : Z
    //   314: aload #5
    //   316: dup
    //   317: astore #5
    //   319: invokevirtual addElement : (Ljava/lang/Object;)V
    //   322: aload_0
    //   323: getfield a : Ljava/util/Vector;
    //   326: aload #5
    //   328: invokevirtual addElement : (Ljava/lang/Object;)V
    //   331: goto -> 439
    //   334: aload #4
    //   336: instanceof dp
    //   339: ifeq -> 423
    //   342: aload #4
    //   344: checkcast dp
    //   347: astore #5
    //   349: aload_0
    //   350: getfield b : Ljava/util/Vector;
    //   353: new fl
    //   356: dup
    //   357: invokespecial <init> : ()V
    //   360: aload #5
    //   362: getfield a : I
    //   365: aload #5
    //   367: getfield b : I
    //   370: invokevirtual a : (II)Lfl;
    //   373: aload #5
    //   375: astore #6
    //   377: dup
    //   378: astore #5
    //   380: aload #6
    //   382: putfield a : Lad;
    //   385: aload #5
    //   387: dup
    //   388: astore #5
    //   390: iconst_1
    //   391: putfield a : B
    //   394: aload #5
    //   396: dup
    //   397: astore #5
    //   399: iconst_1
    //   400: putfield a : Z
    //   403: aload #5
    //   405: dup
    //   406: astore #5
    //   408: invokevirtual addElement : (Ljava/lang/Object;)V
    //   411: aload_0
    //   412: getfield a : Ljava/util/Vector;
    //   415: aload #5
    //   417: invokevirtual addElement : (Ljava/lang/Object;)V
    //   420: goto -> 439
    //   423: aload_0
    //   424: getfield b : Ljava/util/Vector;
    //   427: new iv
    //   430: dup
    //   431: aload #4
    //   433: invokespecial <init> : (Ldv;)V
    //   436: invokevirtual addElement : (Ljava/lang/Object;)V
    //   439: iinc #3, 1
    //   442: goto -> 221
    //   445: aload_1
    //   446: astore_3
    //   447: aload_1
    //   448: invokevirtual a : ()Z
    //   451: ifeq -> 882
    //   454: aload_1
    //   455: getfield a : [Laa;
    //   458: iconst_0
    //   459: aaload
    //   460: dup
    //   461: astore_1
    //   462: ifnull -> 882
    //   465: aload_0
    //   466: getfield b : Ljava/util/Vector;
    //   469: aload_2
    //   470: iconst_2
    //   471: aload_1
    //   472: getfield a : I
    //   475: invokestatic a : (I)Llb;
    //   478: iconst_0
    //   479: iconst_1
    //   480: iconst_1
    //   481: iconst_0
    //   482: iconst_1
    //   483: invokestatic a : (Llb;ZZZZZ)Lr;
    //   486: ldc 'general.repost'
    //   488: invokestatic a : (Ljava/lang/String;)Ljava/lang/String;
    //   491: invokevirtual b : (Ljava/lang/String;)Lr;
    //   494: aload_1
    //   495: getfield b : I
    //   498: invokestatic c : (I)Ljava/lang/String;
    //   501: invokevirtual c : (Ljava/lang/String;)Lr;
    //   504: aload_1
    //   505: invokevirtual d : ()Z
    //   508: ifne -> 532
    //   511: aload_1
    //   512: invokevirtual c : ()Z
    //   515: ifne -> 536
    //   518: aload_1
    //   519: invokevirtual b : ()Z
    //   522: ifne -> 536
    //   525: aload_1
    //   526: invokevirtual a : ()Z
    //   529: ifeq -> 536
    //   532: iconst_1
    //   533: goto -> 537
    //   536: iconst_0
    //   537: istore #6
    //   539: dup
    //   540: astore #5
    //   542: iload #6
    //   544: putfield n : Z
    //   547: aload #5
    //   549: checkcast r
    //   552: dup_x2
    //   553: aastore
    //   554: invokevirtual addElement : (Ljava/lang/Object;)V
    //   557: aload_1
    //   558: invokevirtual d : ()Z
    //   561: ifeq -> 621
    //   564: aload_1
    //   565: getfield c : I
    //   568: aload_1
    //   569: getfield a : I
    //   572: if_icmpeq -> 621
    //   575: aload_0
    //   576: getfield b : Ljava/util/Vector;
    //   579: aload_2
    //   580: iconst_3
    //   581: aload_1
    //   582: getfield c : I
    //   585: invokestatic a : (I)Llb;
    //   588: iconst_1
    //   589: iconst_1
    //   590: iconst_1
    //   591: iconst_0
    //   592: iconst_1
    //   593: invokestatic a : (Llb;ZZZZZ)Lr;
    //   596: ldc 'general.author'
    //   598: invokestatic a : (Ljava/lang/String;)Ljava/lang/String;
    //   601: invokevirtual b : (Ljava/lang/String;)Lr;
    //   604: dup
    //   605: astore #5
    //   607: iconst_0
    //   608: putfield n : Z
    //   611: aload #5
    //   613: checkcast r
    //   616: dup_x2
    //   617: aastore
    //   618: invokevirtual addElement : (Ljava/lang/Object;)V
    //   621: aload_1
    //   622: invokevirtual c : ()Z
    //   625: ifeq -> 646
    //   628: aload_0
    //   629: getfield b : Ljava/util/Vector;
    //   632: new gg
    //   635: dup
    //   636: aload_1
    //   637: getfield a : Ljava/lang/String;
    //   640: invokespecial <init> : (Ljava/lang/String;)V
    //   643: invokevirtual addElement : (Ljava/lang/Object;)V
    //   646: aload_1
    //   647: invokevirtual b : ()Z
    //   650: ifeq -> 882
    //   653: iconst_0
    //   654: istore #4
    //   656: iload #4
    //   658: aload_1
    //   659: getfield a : [Ldv;
    //   662: arraylength
    //   663: if_icmpge -> 882
    //   666: aload_1
    //   667: getfield a : [Ldv;
    //   670: iload #4
    //   672: aaload
    //   673: dup
    //   674: astore #5
    //   676: ifnull -> 876
    //   679: aload #5
    //   681: instanceof jc
    //   684: ifeq -> 771
    //   687: aload #5
    //   689: checkcast jc
    //   692: invokevirtual a : ()Leh;
    //   695: astore #6
    //   697: aload_0
    //   698: getfield b : Ljava/util/Vector;
    //   701: new fl
    //   704: dup
    //   705: invokespecial <init> : ()V
    //   708: aload #6
    //   710: getfield a : I
    //   713: aload #6
    //   715: getfield b : I
    //   718: invokevirtual a : (II)Lfl;
    //   721: aload #5
    //   723: astore #6
    //   725: dup
    //   726: astore #5
    //   728: aload #6
    //   730: putfield a : Lad;
    //   733: aload #5
    //   735: dup
    //   736: astore #5
    //   738: iconst_1
    //   739: putfield a : B
    //   742: aload #5
    //   744: dup
    //   745: astore #5
    //   747: iconst_1
    //   748: putfield a : Z
    //   751: aload #5
    //   753: dup
    //   754: astore #5
    //   756: invokevirtual addElement : (Ljava/lang/Object;)V
    //   759: aload_0
    //   760: getfield a : Ljava/util/Vector;
    //   763: aload #5
    //   765: invokevirtual addElement : (Ljava/lang/Object;)V
    //   768: goto -> 876
    //   771: aload #5
    //   773: instanceof dp
    //   776: ifeq -> 860
    //   779: aload #5
    //   781: checkcast dp
    //   784: astore #6
    //   786: aload_0
    //   787: getfield b : Ljava/util/Vector;
    //   790: new fl
    //   793: dup
    //   794: invokespecial <init> : ()V
    //   797: aload #6
    //   799: getfield a : I
    //   802: aload #6
    //   804: getfield b : I
    //   807: invokevirtual a : (II)Lfl;
    //   810: aload #6
    //   812: astore #6
    //   814: dup
    //   815: astore #5
    //   817: aload #6
    //   819: putfield a : Lad;
    //   822: aload #5
    //   824: dup
    //   825: astore #5
    //   827: iconst_1
    //   828: putfield a : B
    //   831: aload #5
    //   833: dup
    //   834: astore #5
    //   836: iconst_1
    //   837: putfield a : Z
    //   840: aload #5
    //   842: dup
    //   843: astore #5
    //   845: invokevirtual addElement : (Ljava/lang/Object;)V
    //   848: aload_0
    //   849: getfield a : Ljava/util/Vector;
    //   852: aload #5
    //   854: invokevirtual addElement : (Ljava/lang/Object;)V
    //   857: goto -> 876
    //   860: aload_0
    //   861: getfield b : Ljava/util/Vector;
    //   864: new iv
    //   867: dup
    //   868: aload #5
    //   870: invokespecial <init> : (Ldv;)V
    //   873: invokevirtual addElement : (Ljava/lang/Object;)V
    //   876: iinc #4, 1
    //   879: goto -> 656
    //   882: aload_3
    //   883: astore_1
    //   884: aload_0
    //   885: getfield b : Ljava/util/Vector;
    //   888: new fo
    //   891: dup
    //   892: aload_1
    //   893: invokespecial <init> : (Laa;)V
    //   896: invokevirtual addElement : (Ljava/lang/Object;)V
    //   899: aload_0
    //   900: getfield b : Ljava/util/Vector;
    //   903: new ak
    //   906: dup
    //   907: invokespecial <init> : ()V
    //   910: invokevirtual addElement : (Ljava/lang/Object;)V
    //   913: aload_2
    //   914: areturn
  }
  
  public final void d() {
    // Byte code:
    //   0: aload_0
    //   1: iconst_1
    //   2: putfield a : Z
    //   5: getstatic gz.a : Lgz;
    //   8: iconst_1
    //   9: invokevirtual b : (Z)V
    //   12: aload_0
    //   13: getfield a : Llb;
    //   16: ifnull -> 430
    //   19: aload_0
    //   20: getfield a : Llb;
    //   23: getfield d : Z
    //   26: ifeq -> 430
    //   29: aload_0
    //   30: dup
    //   31: astore_1
    //   32: getfield a : Llb;
    //   35: checkcast lk
    //   38: dup
    //   39: astore_2
    //   40: getfield a : Ljava/lang/String;
    //   43: invokestatic a : (Ljava/lang/String;)Z
    //   46: ifne -> 99
    //   49: aload_2
    //   50: getfield a : Ljava/lang/String;
    //   53: ldc 'deleted'
    //   55: invokevirtual equals : (Ljava/lang/Object;)Z
    //   58: ifeq -> 80
    //   61: aload_1
    //   62: new gg
    //   65: dup
    //   66: ldc 'element.pageDeleted'
    //   68: invokestatic a : (Ljava/lang/String;)Ljava/lang/String;
    //   71: invokespecial <init> : (Ljava/lang/String;)V
    //   74: invokespecial b : (Lay;)V
    //   77: goto -> 951
    //   80: aload_1
    //   81: new gg
    //   84: dup
    //   85: ldc 'element.pageBanned'
    //   87: invokestatic a : (Ljava/lang/String;)Ljava/lang/String;
    //   90: invokespecial <init> : (Ljava/lang/String;)V
    //   93: invokespecial b : (Lay;)V
    //   96: goto -> 951
    //   99: aload_1
    //   100: aload_2
    //   101: iconst_0
    //   102: iconst_1
    //   103: iconst_0
    //   104: iconst_1
    //   105: iconst_1
    //   106: invokestatic a : (Llb;ZZZZZ)Lr;
    //   109: ldc 'element.community'
    //   111: invokestatic a : (Ljava/lang/String;)Ljava/lang/String;
    //   114: invokevirtual c : (Ljava/lang/String;)Lr;
    //   117: invokespecial b : (Lay;)V
    //   120: aload_2
    //   121: getfield b : Ljava/lang/String;
    //   124: invokestatic a : (Ljava/lang/String;)Z
    //   127: ifne -> 159
    //   130: aload_1
    //   131: new gg
    //   134: dup
    //   135: aload_2
    //   136: getfield b : Ljava/lang/String;
    //   139: invokespecial <init> : (Ljava/lang/String;)V
    //   142: dup
    //   143: astore_3
    //   144: iconst_0
    //   145: putfield m : Z
    //   148: aload_3
    //   149: dup
    //   150: astore_3
    //   151: iconst_1
    //   152: putfield r : Z
    //   155: aload_3
    //   156: invokespecial b : (Lay;)V
    //   159: aload_2
    //   160: getfield a : Z
    //   163: ifeq -> 185
    //   166: aload_1
    //   167: new gg
    //   170: dup
    //   171: ldc 'element.groupBlacklisted'
    //   173: invokestatic a : (Ljava/lang/String;)Ljava/lang/String;
    //   176: invokespecial <init> : (Ljava/lang/String;)V
    //   179: invokespecial b : (Lay;)V
    //   182: goto -> 951
    //   185: aload_2
    //   186: getfield b : Z
    //   189: ifne -> 242
    //   192: aload_2
    //   193: getfield b : I
    //   196: ifeq -> 242
    //   199: aload_2
    //   200: getfield b : I
    //   203: iconst_1
    //   204: if_icmpne -> 226
    //   207: aload_1
    //   208: new gg
    //   211: dup
    //   212: ldc 'element.groupClosed'
    //   214: invokestatic a : (Ljava/lang/String;)Ljava/lang/String;
    //   217: invokespecial <init> : (Ljava/lang/String;)V
    //   220: invokespecial b : (Lay;)V
    //   223: goto -> 242
    //   226: aload_1
    //   227: new gg
    //   230: dup
    //   231: ldc 'element.groupPrivate'
    //   233: invokestatic a : (Ljava/lang/String;)Ljava/lang/String;
    //   236: invokespecial <init> : (Ljava/lang/String;)V
    //   239: invokespecial b : (Lay;)V
    //   242: aload_2
    //   243: getfield b : Z
    //   246: ifne -> 257
    //   249: aload_2
    //   250: getfield b : I
    //   253: iconst_2
    //   254: if_icmpeq -> 310
    //   257: aload_2
    //   258: getfield b : Z
    //   261: ifeq -> 269
    //   264: ldc 'Покинуть группу'
    //   266: goto -> 295
    //   269: aload_2
    //   270: getfield b : I
    //   273: ifne -> 281
    //   276: ldc 'Вступить в группу'
    //   278: goto -> 295
    //   281: aload_2
    //   282: getfield c : I
    //   285: ifeq -> 293
    //   288: ldc 'Принять приглашение'
    //   290: goto -> 295
    //   293: ldc 'Отправить заявку'
    //   295: astore_3
    //   296: aload_1
    //   297: new em
    //   300: dup
    //   301: aload_1
    //   302: aload_3
    //   303: aload_2
    //   304: invokespecial <init> : (Li;Ljava/lang/String;Llk;)V
    //   307: invokespecial b : (Lay;)V
    //   310: aload_2
    //   311: getfield b : Z
    //   314: ifne -> 324
    //   317: aload_2
    //   318: getfield b : I
    //   321: ifne -> 427
    //   324: aload_2
    //   325: getfield c : Z
    //   328: ifeq -> 348
    //   331: aload_1
    //   332: new el
    //   335: dup
    //   336: aload_1
    //   337: ldc 'action.writeMessage'
    //   339: invokestatic a : (Ljava/lang/String;)Ljava/lang/String;
    //   342: invokespecial <init> : (Li;Ljava/lang/String;)V
    //   345: invokespecial b : (Lay;)V
    //   348: aload_2
    //   349: getfield e : I
    //   352: ifle -> 396
    //   355: aload_1
    //   356: new bu
    //   359: dup
    //   360: aload_1
    //   361: ldc 'elements.audios'
    //   363: invokestatic a : (Ljava/lang/String;)Ljava/lang/String;
    //   366: invokespecial <init> : (Li;Ljava/lang/String;)V
    //   369: ldc 'mm.png'
    //   371: ldc 'mms.png'
    //   373: invokevirtual a : (Ljava/lang/String;Ljava/lang/String;)Lr;
    //   376: aload_2
    //   377: getfield e : I
    //   380: invokestatic b : (I)Ljava/lang/String;
    //   383: invokevirtual b : (Ljava/lang/String;)Lr;
    //   386: dup
    //   387: astore_3
    //   388: iconst_1
    //   389: putfield n : Z
    //   392: aload_3
    //   393: invokespecial b : (Lay;)V
    //   396: aload_1
    //   397: aload_1
    //   398: getfield a : Lr;
    //   401: invokespecial b : (Lay;)V
    //   404: aload_1
    //   405: new ak
    //   408: dup
    //   409: invokespecial <init> : ()V
    //   412: dup
    //   413: astore_3
    //   414: iconst_1
    //   415: putfield p : Z
    //   418: aload_3
    //   419: invokespecial b : (Lay;)V
    //   422: aload_1
    //   423: iconst_0
    //   424: putfield b : Z
    //   427: goto -> 951
    //   430: aload_0
    //   431: dup
    //   432: astore_1
    //   433: getfield a : Llb;
    //   436: checkcast bi
    //   439: dup
    //   440: astore_2
    //   441: getfield b : Ljava/lang/String;
    //   444: invokestatic a : (Ljava/lang/String;)Z
    //   447: ifne -> 500
    //   450: aload_2
    //   451: getfield b : Ljava/lang/String;
    //   454: ldc 'deleted'
    //   456: invokevirtual equals : (Ljava/lang/Object;)Z
    //   459: ifeq -> 481
    //   462: aload_1
    //   463: new gg
    //   466: dup
    //   467: ldc 'element.pageDeleted'
    //   469: invokestatic a : (Ljava/lang/String;)Ljava/lang/String;
    //   472: invokespecial <init> : (Ljava/lang/String;)V
    //   475: invokespecial b : (Lay;)V
    //   478: goto -> 951
    //   481: aload_1
    //   482: new gg
    //   485: dup
    //   486: ldc 'element.pageBanned'
    //   488: invokestatic a : (Ljava/lang/String;)Ljava/lang/String;
    //   491: invokespecial <init> : (Ljava/lang/String;)V
    //   494: invokespecial b : (Lay;)V
    //   497: goto -> 951
    //   500: aload_1
    //   501: aload_2
    //   502: iconst_0
    //   503: iconst_1
    //   504: iconst_0
    //   505: iconst_1
    //   506: iconst_1
    //   507: invokestatic a : (Llb;ZZZZZ)Lr;
    //   510: invokespecial b : (Lay;)V
    //   513: aload_2
    //   514: getfield c : Ljava/lang/String;
    //   517: invokestatic a : (Ljava/lang/String;)Z
    //   520: ifne -> 552
    //   523: aload_1
    //   524: new gg
    //   527: dup
    //   528: aload_2
    //   529: getfield c : Ljava/lang/String;
    //   532: invokespecial <init> : (Ljava/lang/String;)V
    //   535: dup
    //   536: astore_3
    //   537: iconst_0
    //   538: putfield m : Z
    //   541: aload_3
    //   542: dup
    //   543: astore_3
    //   544: iconst_1
    //   545: putfield r : Z
    //   548: aload_3
    //   549: invokespecial b : (Lay;)V
    //   552: aload_2
    //   553: getfield b : Z
    //   556: ifeq -> 578
    //   559: aload_1
    //   560: new gg
    //   563: dup
    //   564: ldc 'element.userBlacklisted'
    //   566: invokestatic a : (Ljava/lang/String;)Ljava/lang/String;
    //   569: invokespecial <init> : (Ljava/lang/String;)V
    //   572: invokespecial b : (Lay;)V
    //   575: goto -> 951
    //   578: aload_2
    //   579: getfield g : I
    //   582: tableswitch default -> 635, 1 -> 626, 2 -> 617, 3 -> 608
    //   608: ldc 'action.removeFromFriends'
    //   610: invokestatic a : (Ljava/lang/String;)Ljava/lang/String;
    //   613: astore_3
    //   614: goto -> 641
    //   617: ldc 'action.acceptFriendsRequest'
    //   619: invokestatic a : (Ljava/lang/String;)Ljava/lang/String;
    //   622: astore_3
    //   623: goto -> 641
    //   626: ldc 'action.cancelFriendsRequest'
    //   628: invokestatic a : (Ljava/lang/String;)Ljava/lang/String;
    //   631: astore_3
    //   632: goto -> 641
    //   635: ldc 'action.addToFriends'
    //   637: invokestatic a : (Ljava/lang/String;)Ljava/lang/String;
    //   640: astore_3
    //   641: aload_2
    //   642: invokevirtual a : ()I
    //   645: getstatic fy.a : Liq;
    //   648: getfield a : I
    //   651: if_icmpeq -> 668
    //   654: aload_1
    //   655: new bv
    //   658: dup
    //   659: aload_1
    //   660: aload_3
    //   661: aload_2
    //   662: invokespecial <init> : (Li;Ljava/lang/String;Lbi;)V
    //   665: invokespecial b : (Lay;)V
    //   668: aload_2
    //   669: getfield c : Z
    //   672: ifeq -> 705
    //   675: aload_2
    //   676: invokevirtual a : ()I
    //   679: getstatic fy.a : Liq;
    //   682: getfield a : I
    //   685: if_icmpeq -> 705
    //   688: aload_1
    //   689: new br
    //   692: dup
    //   693: aload_1
    //   694: ldc 'action.writeMessage'
    //   696: invokestatic a : (Ljava/lang/String;)Ljava/lang/String;
    //   699: invokespecial <init> : (Li;Ljava/lang/String;)V
    //   702: invokespecial b : (Lay;)V
    //   705: aload_1
    //   706: new ak
    //   709: dup
    //   710: invokespecial <init> : ()V
    //   713: dup
    //   714: astore_3
    //   715: iconst_1
    //   716: putfield p : Z
    //   719: aload_3
    //   720: invokespecial b : (Lay;)V
    //   723: aload_2
    //   724: getfield i : I
    //   727: ifle -> 824
    //   730: aload_1
    //   731: new bt
    //   734: dup
    //   735: aload_1
    //   736: ldc 'elements.friends'
    //   738: invokestatic a : (Ljava/lang/String;)Ljava/lang/String;
    //   741: invokespecial <init> : (Li;Ljava/lang/String;)V
    //   744: ldc 'mf.png'
    //   746: ldc 'mfs.png'
    //   748: invokevirtual a : (Ljava/lang/String;Ljava/lang/String;)Lr;
    //   751: new java/lang/StringBuffer
    //   754: dup
    //   755: invokespecial <init> : ()V
    //   758: aload_2
    //   759: getfield k : I
    //   762: ifle -> 793
    //   765: new java/lang/StringBuffer
    //   768: dup
    //   769: invokespecial <init> : ()V
    //   772: aload_2
    //   773: getfield k : I
    //   776: invokestatic b : (I)Ljava/lang/String;
    //   779: invokevirtual append : (Ljava/lang/String;)Ljava/lang/StringBuffer;
    //   782: ldc ' / '
    //   784: invokevirtual append : (Ljava/lang/String;)Ljava/lang/StringBuffer;
    //   787: invokevirtual toString : ()Ljava/lang/String;
    //   790: goto -> 795
    //   793: ldc ''
    //   795: invokevirtual append : (Ljava/lang/String;)Ljava/lang/StringBuffer;
    //   798: aload_2
    //   799: getfield i : I
    //   802: invokestatic b : (I)Ljava/lang/String;
    //   805: invokevirtual append : (Ljava/lang/String;)Ljava/lang/StringBuffer;
    //   808: invokevirtual toString : ()Ljava/lang/String;
    //   811: invokevirtual b : (Ljava/lang/String;)Lr;
    //   814: dup
    //   815: astore_3
    //   816: iconst_1
    //   817: putfield n : Z
    //   820: aload_3
    //   821: invokespecial b : (Lay;)V
    //   824: aload_2
    //   825: getfield j : I
    //   828: ifle -> 872
    //   831: aload_1
    //   832: new bp
    //   835: dup
    //   836: aload_1
    //   837: ldc 'elements.groups'
    //   839: invokestatic a : (Ljava/lang/String;)Ljava/lang/String;
    //   842: invokespecial <init> : (Li;Ljava/lang/String;)V
    //   845: ldc 'mg.png'
    //   847: ldc 'mgs.png'
    //   849: invokevirtual a : (Ljava/lang/String;Ljava/lang/String;)Lr;
    //   852: aload_2
    //   853: getfield j : I
    //   856: invokestatic b : (I)Ljava/lang/String;
    //   859: invokevirtual b : (Ljava/lang/String;)Lr;
    //   862: dup
    //   863: astore_3
    //   864: iconst_1
    //   865: putfield n : Z
    //   868: aload_3
    //   869: invokespecial b : (Lay;)V
    //   872: aload_2
    //   873: getfield h : I
    //   876: ifle -> 920
    //   879: aload_1
    //   880: new bl
    //   883: dup
    //   884: aload_1
    //   885: ldc 'elements.audios'
    //   887: invokestatic a : (Ljava/lang/String;)Ljava/lang/String;
    //   890: invokespecial <init> : (Li;Ljava/lang/String;)V
    //   893: ldc 'mm.png'
    //   895: ldc 'mms.png'
    //   897: invokevirtual a : (Ljava/lang/String;Ljava/lang/String;)Lr;
    //   900: aload_2
    //   901: getfield h : I
    //   904: invokestatic b : (I)Ljava/lang/String;
    //   907: invokevirtual b : (Ljava/lang/String;)Lr;
    //   910: dup
    //   911: astore_3
    //   912: iconst_1
    //   913: putfield n : Z
    //   916: aload_3
    //   917: invokespecial b : (Lay;)V
    //   920: aload_1
    //   921: aload_1
    //   922: getfield a : Lr;
    //   925: invokespecial b : (Lay;)V
    //   928: aload_1
    //   929: new ak
    //   932: dup
    //   933: invokespecial <init> : ()V
    //   936: dup
    //   937: astore_3
    //   938: iconst_1
    //   939: putfield p : Z
    //   942: aload_3
    //   943: invokespecial b : (Lay;)V
    //   946: aload_1
    //   947: iconst_0
    //   948: putfield b : Z
    //   951: aload_0
    //   952: iconst_0
    //   953: putfield a : Z
    //   956: aload_0
    //   957: iconst_1
    //   958: putfield c : Z
    //   961: getstatic gz.a : Lgz;
    //   964: iconst_0
    //   965: invokevirtual b : (Z)V
    //   968: aload_0
    //   969: invokevirtual b : ()V
    //   972: return
  }
  
  public static String a(int paramInt) {
    if (paramInt % 100 / 10 == 1)
      return u.a("element.followersCount", paramInt + ""); 
    switch (paramInt % 10) {
      case 1:
        return u.a("element.followersCountOne", paramInt + "");
      case 2:
      case 3:
      case 4:
        return u.a("element.followersCountSome", paramInt + "");
    } 
    return u.a("element.followersCount", paramInt + "");
  }
  
  public static String b(int paramInt) {
    return ((paramInt = paramInt) == 0) ? "" : ((paramInt < 10000) ? (paramInt + "") : ((paramInt < 1000000) ? ((paramInt / 1000) + "K") : ((paramInt / 1000000) + "M")));
  }
  
  public static String c(int paramInt) {
    long l = System.currentTimeMillis() / 1000L / 86400L - (paramInt / 86400);
    int[] arrayOfInt = ab.a(paramInt);
    return ((l > 1L) ? (ab.a(arrayOfInt[3]) + "." + ab.a(arrayOfInt[4]) + u.a("general.dateAt")) : ((arrayOfInt == 1L) ? u.a("general.yesterdayAt") : u.a("general.todayAt"))) + ab.b(paramInt);
  }
  
  public static String a(boolean paramBoolean, int paramInt) {
    return u.a("element.lastSeen" + (paramBoolean ? "Male" : "Female"), c(paramInt));
  }
  
  static void e() {
    // Byte code:
    //   0: getstatic i.a : Li;
    //   3: ifnull -> 39
    //   6: getstatic i.a : Li;
    //   9: getfield a : Ljava/util/Vector;
    //   12: ifnull -> 39
    //   15: getstatic gz.a : Lgz;
    //   18: getfield a : Lla;
    //   21: instanceof i
    //   24: ifeq -> 39
    //   27: getstatic gz.a : Lgz;
    //   30: getfield a : Lkz;
    //   33: getfield a : Z
    //   36: ifeq -> 52
    //   39: ldc2_w 3000
    //   42: invokestatic sleep : (J)V
    //   45: goto -> 0
    //   48: pop
    //   49: goto -> 0
    //   52: iconst_0
    //   53: istore_0
    //   54: iload_0
    //   55: getstatic i.a : Li;
    //   58: getfield a : Ljava/util/Vector;
    //   61: invokevirtual size : ()I
    //   64: if_icmpge -> 179
    //   67: getstatic i.a : Li;
    //   70: getfield a : Ljava/util/Vector;
    //   73: iload_0
    //   74: invokevirtual elementAt : (I)Ljava/lang/Object;
    //   77: checkcast fl
    //   80: astore_1
    //   81: aload_1
    //   82: getfield a : Lad;
    //   85: instanceof jc
    //   88: ifeq -> 114
    //   91: aload_1
    //   92: aload_1
    //   93: getfield a : Lad;
    //   96: checkcast jc
    //   99: invokevirtual a : ()Leh;
    //   102: getfield b : Ljava/lang/String;
    //   105: invokestatic b : (Ljava/lang/String;)Ljavax/microedition/lcdui/Image;
    //   108: invokevirtual a : (Ljavax/microedition/lcdui/Image;)V
    //   111: goto -> 145
    //   114: aload_1
    //   115: getfield a : Lad;
    //   118: instanceof dp
    //   121: ifeq -> 141
    //   124: aload_1
    //   125: aload_1
    //   126: getfield a : Lad;
    //   129: checkcast dp
    //   132: getfield a : Ljava/lang/String;
    //   135: invokestatic b : (Ljava/lang/String;)Ljavax/microedition/lcdui/Image;
    //   138: invokevirtual a : (Ljavax/microedition/lcdui/Image;)V
    //   141: goto -> 145
    //   144: pop
    //   145: getstatic i.a : Li;
    //   148: getfield a : Ljava/util/Vector;
    //   151: iload_0
    //   152: invokevirtual removeElementAt : (I)V
    //   155: getstatic gz.a : Lgz;
    //   158: getfield a : Lla;
    //   161: instanceof bc
    //   164: ifeq -> 173
    //   167: getstatic gz.a : Lgz;
    //   170: invokevirtual b : ()V
    //   173: iinc #0, 1
    //   176: goto -> 54
    //   179: ldc2_w 3000
    //   182: invokestatic sleep : (J)V
    //   185: goto -> 0
    //   188: pop
    //   189: goto -> 0
    //   192: pop
    //   193: getstatic i.a : Li;
    //   196: getfield a : Ljava/util/Vector;
    //   199: invokevirtual removeAllElements : ()V
    //   202: invokestatic gc : ()V
    //   205: goto -> 0
    //   208: pop
    //   209: goto -> 0
    // Exception table:
    //   from	to	target	type
    //   0	49	192	java/lang/OutOfMemoryError
    //   0	49	208	java/lang/Exception
    //   39	45	48	java/lang/Exception
    //   52	189	192	java/lang/OutOfMemoryError
    //   52	189	208	java/lang/Exception
    //   81	141	144	java/lang/Exception
    //   179	185	188	java/lang/Exception
  }
  
  static {
    // Byte code:
    //   0: getstatic i.a : Ljava/lang/Thread;
    //   3: ifnonnull -> 27
    //   6: new eu
    //   9: dup
    //   10: invokespecial <init> : ()V
    //   13: dup
    //   14: putstatic i.a : Ljava/lang/Thread;
    //   17: iconst_1
    //   18: invokevirtual setPriority : (I)V
    //   21: getstatic i.a : Ljava/lang/Thread;
    //   24: invokevirtual start : ()V
    //   27: return
  }
}


/* Location:              /home/kost/Загрузки/latest.jar!/i.class
 * Java compiler version: 4 (48.0)
 * JD-Core Version:       1.1.3
 */