final class jj extends Thread {
  private final la a;
  
  jj(la paramla) {
    this.a = paramla;
  }
  
  public final void run() {
    // Byte code:
    //   0: aload_0
    //   1: getfield a : Lla;
    //   4: astore_1
    //   5: invokestatic a : ()V
    //   8: getstatic ci.a : Z
    //   11: ifeq -> 33
    //   14: aload_1
    //   15: getfield b : Ljava/util/Vector;
    //   18: iconst_4
    //   19: invokevirtual elementAt : (I)Ljava/lang/Object;
    //   22: checkcast r
    //   25: ldc 'mpn.png'
    //   27: ldc 'mpns.png'
    //   29: invokevirtual a : (Ljava/lang/String;Ljava/lang/String;)Lr;
    //   32: pop
    //   33: iconst_0
    //   34: iconst_1
    //   35: invokestatic a : (IZ)Llb;
    //   38: checkcast bi
    //   41: astore_2
    //   42: aload_1
    //   43: getfield b : Ljava/util/Vector;
    //   46: iconst_0
    //   47: invokevirtual elementAt : (I)Ljava/lang/Object;
    //   50: checkcast r
    //   53: aload_2
    //   54: ldc 'nom'
    //   56: invokevirtual b : (Ljava/lang/String;)Ljava/lang/String;
    //   59: invokevirtual a : (Ljava/lang/String;)Lr;
    //   62: aload_2
    //   63: invokevirtual a : ()Z
    //   66: ifeq -> 76
    //   69: aload_2
    //   70: getfield c : Ljava/lang/String;
    //   73: goto -> 81
    //   76: ldc 'element.yourProfile'
    //   78: invokestatic a : (Ljava/lang/String;)Ljava/lang/String;
    //   81: invokevirtual c : (Ljava/lang/String;)Lr;
    //   84: aload_2
    //   85: invokevirtual a : ()I
    //   88: invokestatic a : (I)Ljavax/microedition/lcdui/Image;
    //   91: aconst_null
    //   92: invokevirtual a : (Ljavax/microedition/lcdui/Image;Ljavax/microedition/lcdui/Image;)Lr;
    //   95: pop
    //   96: aload_1
    //   97: getfield b : Ljava/util/Vector;
    //   100: iconst_1
    //   101: invokevirtual elementAt : (I)Ljava/lang/Object;
    //   104: checkcast r
    //   107: new java/lang/StringBuffer
    //   110: dup
    //   111: invokespecial <init> : ()V
    //   114: aload_2
    //   115: getfield k : I
    //   118: ifle -> 149
    //   121: new java/lang/StringBuffer
    //   124: dup
    //   125: invokespecial <init> : ()V
    //   128: aload_2
    //   129: getfield k : I
    //   132: invokestatic b : (I)Ljava/lang/String;
    //   135: invokevirtual append : (Ljava/lang/String;)Ljava/lang/StringBuffer;
    //   138: ldc ' / '
    //   140: invokevirtual append : (Ljava/lang/String;)Ljava/lang/StringBuffer;
    //   143: invokevirtual toString : ()Ljava/lang/String;
    //   146: goto -> 151
    //   149: ldc ''
    //   151: invokevirtual append : (Ljava/lang/String;)Ljava/lang/StringBuffer;
    //   154: aload_2
    //   155: getfield i : I
    //   158: invokestatic b : (I)Ljava/lang/String;
    //   161: invokevirtual append : (Ljava/lang/String;)Ljava/lang/StringBuffer;
    //   164: invokevirtual toString : ()Ljava/lang/String;
    //   167: invokevirtual b : (Ljava/lang/String;)Lr;
    //   170: pop
    //   171: aload_1
    //   172: getfield b : Ljava/util/Vector;
    //   175: iconst_2
    //   176: invokevirtual elementAt : (I)Ljava/lang/Object;
    //   179: checkcast r
    //   182: aload_2
    //   183: getfield j : I
    //   186: invokestatic b : (I)Ljava/lang/String;
    //   189: invokevirtual b : (Ljava/lang/String;)Lr;
    //   192: pop
    //   193: aload_1
    //   194: getfield b : Ljava/util/Vector;
    //   197: iconst_3
    //   198: invokevirtual elementAt : (I)Ljava/lang/Object;
    //   201: checkcast r
    //   204: aload_2
    //   205: getfield h : I
    //   208: invokestatic b : (I)Ljava/lang/String;
    //   211: invokevirtual b : (Ljava/lang/String;)Lr;
    //   214: pop
    //   215: aload_2
    //   216: getfield a : Ljava/lang/String;
    //   219: ifnull -> 290
    //   222: invokestatic a : ()J
    //   225: invokestatic a : (J)[I
    //   228: astore_3
    //   229: aload_2
    //   230: getfield a : Ljava/lang/String;
    //   233: invokestatic a : (Ljava/lang/String;)[I
    //   236: dup
    //   237: astore_2
    //   238: iconst_3
    //   239: iaload
    //   240: aload_3
    //   241: iconst_3
    //   242: iaload
    //   243: if_icmpne -> 290
    //   246: aload_2
    //   247: iconst_4
    //   248: iaload
    //   249: aload_3
    //   250: iconst_4
    //   251: iaload
    //   252: if_icmpne -> 290
    //   255: aload_1
    //   256: getfield b : Ljava/util/Vector;
    //   259: new r
    //   262: dup
    //   263: ldc 'event.happyBirthday'
    //   265: invokestatic a : (Ljava/lang/String;)Ljava/lang/String;
    //   268: iconst_0
    //   269: invokespecial <init> : (Ljava/lang/String;B)V
    //   272: ldc 'event.happyBirthdayCongratulation'
    //   274: invokestatic a : (Ljava/lang/String;)Ljava/lang/String;
    //   277: invokevirtual c : (Ljava/lang/String;)Lr;
    //   280: ldc 'gift.png'
    //   282: ldc 'gifts.png'
    //   284: invokevirtual a : (Ljava/lang/String;Ljava/lang/String;)Lr;
    //   287: invokevirtual addElement : (Ljava/lang/Object;)V
    //   290: getstatic gz.a : Lgz;
    //   293: invokevirtual b : ()V
    //   296: return
  }
}


/* Location:              /home/kost/Загрузки/latest.jar!/jj.class
 * Java compiler version: 4 (48.0)
 * JD-Core Version:       1.1.3
 */