final class jk extends jr {
  private final int a;
  
  jk(String paramString, int paramInt) {
    super(paramString);
    this.a = paramInt;
  }
  
  public final void c() {
    // Byte code:
    //   0: getstatic fw.a : Lgz;
    //   3: iconst_1
    //   4: invokevirtual b : (Z)V
    //   7: aload_0
    //   8: getfield a : Ljava/lang/Object;
    //   11: ifnonnull -> 18
    //   14: iconst_1
    //   15: goto -> 19
    //   18: iconst_0
    //   19: ifeq -> 34
    //   22: aload_0
    //   23: new java/lang/Integer
    //   26: dup
    //   27: iconst_m1
    //   28: invokespecial <init> : (I)V
    //   31: putfield a : Ljava/lang/Object;
    //   34: aload_0
    //   35: new java/lang/Integer
    //   38: dup
    //   39: aload_0
    //   40: getfield a : Ljava/lang/Object;
    //   43: checkcast java/lang/Integer
    //   46: invokevirtual intValue : ()I
    //   49: iconst_1
    //   50: iadd
    //   51: invokespecial <init> : (I)V
    //   54: putfield a : Ljava/lang/Object;
    //   57: new java/util/Vector
    //   60: dup
    //   61: invokespecial <init> : ()V
    //   64: astore_1
    //   65: aload_0
    //   66: getfield a : Ljava/lang/Object;
    //   69: checkcast java/lang/Integer
    //   72: invokevirtual intValue : ()I
    //   75: bipush #20
    //   77: imul
    //   78: istore_2
    //   79: new fx
    //   82: dup
    //   83: invokespecial <init> : ()V
    //   86: aload_0
    //   87: getfield a : I
    //   90: invokevirtual a : (I)Lfx;
    //   93: bipush #20
    //   95: invokevirtual c : (I)Lfx;
    //   98: iload_2
    //   99: invokevirtual b : (I)Lfx;
    //   102: invokevirtual a : ()Laj;
    //   105: checkcast gs
    //   108: dup
    //   109: astore_3
    //   110: ifnull -> 298
    //   113: aload_3
    //   114: invokevirtual b : ()Z
    //   117: ifeq -> 298
    //   120: aload_3
    //   121: getfield a : [Lcm;
    //   124: arraylength
    //   125: bipush #20
    //   127: if_icmpge -> 135
    //   130: aload_0
    //   131: iconst_1
    //   132: putfield b : Z
    //   135: iconst_0
    //   136: istore #4
    //   138: iload #4
    //   140: aload_3
    //   141: getfield a : [Lcm;
    //   144: arraylength
    //   145: if_icmpge -> 283
    //   148: aload_3
    //   149: getfield a : [Lcm;
    //   152: iload #4
    //   154: aaload
    //   155: new jm
    //   158: dup
    //   159: aload_0
    //   160: getfield a : I
    //   163: invokespecial <init> : (I)V
    //   166: iload #4
    //   168: iload_2
    //   169: iadd
    //   170: istore #7
    //   172: astore #6
    //   174: astore #5
    //   176: new gv
    //   179: dup
    //   180: aload #6
    //   182: iload #7
    //   184: invokespecial <init> : (Ljm;I)V
    //   187: aload #5
    //   189: invokevirtual a : (Lad;)Lr;
    //   192: iconst_1
    //   193: iconst_0
    //   194: invokevirtual a : (ZZ)Lr;
    //   197: iconst_1
    //   198: invokevirtual a : (Z)Lr;
    //   201: aload #5
    //   203: getfield c : Ljava/lang/String;
    //   206: invokevirtual a : (Ljava/lang/String;)Lr;
    //   209: aload #5
    //   211: getfield b : Ljava/lang/String;
    //   214: invokevirtual c : (Ljava/lang/String;)Lr;
    //   217: aload #5
    //   219: getfield a : I
    //   222: i2l
    //   223: invokestatic a : (J)Ljava/lang/String;
    //   226: invokevirtual b : (Ljava/lang/String;)Lr;
    //   229: getstatic hx.b : Ljavax/microedition/lcdui/Image;
    //   232: aconst_null
    //   233: invokevirtual a : (Ljavax/microedition/lcdui/Image;Ljavax/microedition/lcdui/Image;)Lr;
    //   236: dup
    //   237: astore #5
    //   239: iconst_1
    //   240: putfield n : Z
    //   243: aload #5
    //   245: checkcast r
    //   248: dup
    //   249: astore #5
    //   251: iconst_1
    //   252: putfield n : Z
    //   255: aload #5
    //   257: checkcast r
    //   260: astore #5
    //   262: aload_1
    //   263: aload #5
    //   265: invokevirtual addElement : (Ljava/lang/Object;)V
    //   268: aload_0
    //   269: getfield b : Ljava/util/Vector;
    //   272: aload #5
    //   274: invokevirtual addElement : (Ljava/lang/Object;)V
    //   277: iinc #4, 1
    //   280: goto -> 138
    //   283: new ib
    //   286: dup
    //   287: aload_1
    //   288: aload_3
    //   289: invokespecial <init> : (Ljava/util/Vector;Lgs;)V
    //   292: invokevirtual start : ()V
    //   295: goto -> 318
    //   298: aload_0
    //   299: iconst_1
    //   300: putfield b : Z
    //   303: aload_3
    //   304: ifnonnull -> 318
    //   307: getstatic gz.a : Lgz;
    //   310: ldc 'general.loadError'
    //   312: invokestatic a : (Ljava/lang/String;)Ljava/lang/String;
    //   315: invokevirtual a : (Ljava/lang/String;)V
    //   318: getstatic fw.a : Lgz;
    //   321: iconst_0
    //   322: invokevirtual b : (Z)V
    //   325: return
  }
}


/* Location:              /home/kost/Загрузки/latest.jar!/jk.class
 * Java compiler version: 4 (48.0)
 * JD-Core Version:       1.1.3
 */