final class ka extends la {
  final ci a;
  
  private ka(ci paramci, byte paramByte) {
    // Byte code:
    //   0: aload_0
    //   1: ldc 'title.localizationSettings'
    //   3: invokestatic a : (Ljava/lang/String;)Ljava/lang/String;
    //   6: invokespecial <init> : (Ljava/lang/String;)V
    //   9: aload_0
    //   10: aload_1
    //   11: putfield a : Lci;
    //   14: aload_0
    //   15: iconst_1
    //   16: invokevirtual a : (Z)Lla;
    //   19: pop
    //   20: aload_0
    //   21: ldc 'action.back'
    //   23: invokestatic a : (Ljava/lang/String;)Ljava/lang/String;
    //   26: new gf
    //   29: dup
    //   30: aload_0
    //   31: invokespecial <init> : (Lka;)V
    //   34: iconst_1
    //   35: invokestatic a : (Lla;Ljava/lang/String;Ljava/lang/Runnable;Z)V
    //   38: aload_0
    //   39: getfield b : Ljava/util/Vector;
    //   42: new ak
    //   45: dup
    //   46: invokespecial <init> : ()V
    //   49: invokevirtual addElement : (Ljava/lang/Object;)V
    //   52: invokestatic a : ()Ljava/util/Vector;
    //   55: astore_2
    //   56: iconst_0
    //   57: istore_1
    //   58: iload_1
    //   59: aload_2
    //   60: invokevirtual size : ()I
    //   63: if_icmpge -> 172
    //   66: aload_2
    //   67: iload_1
    //   68: invokevirtual elementAt : (I)Ljava/lang/Object;
    //   71: checkcast fg
    //   74: astore_3
    //   75: aload_0
    //   76: getfield b : Ljava/util/Vector;
    //   79: new gc
    //   82: dup
    //   83: aload_0
    //   84: aload_3
    //   85: getfield b : Ljava/lang/String;
    //   88: aload_3
    //   89: invokespecial <init> : (Lka;Ljava/lang/String;Lfg;)V
    //   92: ldc 'settings.localizationBy'
    //   94: aload_3
    //   95: getfield c : Ljava/lang/String;
    //   98: invokestatic a : (Ljava/lang/String;Ljava/lang/String;)Ljava/lang/String;
    //   101: invokevirtual c : (Ljava/lang/String;)Lr;
    //   104: iconst_0
    //   105: iconst_0
    //   106: invokevirtual a : (ZZ)Lr;
    //   109: aload_3
    //   110: getfield d : Ljava/lang/String;
    //   113: invokevirtual b : (Ljava/lang/String;)Lr;
    //   116: getstatic ci.a : Lv;
    //   119: getfield a : Ljava/lang/String;
    //   122: ifnull -> 145
    //   125: getstatic ci.a : Lv;
    //   128: getfield a : Ljava/lang/String;
    //   131: aload_3
    //   132: getfield a : Ljava/lang/String;
    //   135: invokevirtual equals : (Ljava/lang/Object;)Z
    //   138: ifeq -> 145
    //   141: iconst_1
    //   142: goto -> 146
    //   145: iconst_0
    //   146: invokevirtual b : (Z)Lr;
    //   149: dup
    //   150: astore_3
    //   151: iconst_1
    //   152: putfield o : Z
    //   155: aload_3
    //   156: dup
    //   157: astore_3
    //   158: iconst_1
    //   159: putfield n : Z
    //   162: aload_3
    //   163: invokevirtual addElement : (Ljava/lang/Object;)V
    //   166: iinc #1, 1
    //   169: goto -> 58
    //   172: aload_0
    //   173: astore_1
    //   174: getstatic gz.a : Lgz;
    //   177: aload_1
    //   178: invokevirtual b : (Lla;)V
    //   181: return
  }
  
  ka(ci paramci) {
    this(paramci, (byte)0);
  }
}


/* Location:              /home/kost/Загрузки/latest.jar!/ka.class
 * Java compiler version: 4 (48.0)
 * JD-Core Version:       1.1.3
 */