import java.util.Hashtable;
import javax.microedition.lcdui.Graphics;
import javax.microedition.lcdui.Image;

public final class kp {
  private static Hashtable a = new Hashtable();
  
  private static Image[] a = new Image[6];
  
  private static Image[] b = new Image[6];
  
  private static Image a;
  
  private static Image b;
  
  private static Image c;
  
  private static Image d;
  
  private static Image e;
  
  private static Image f;
  
  private static Image g;
  
  private static Image h;
  
  private static Image i;
  
  private static Image[] c;
  
  private static int b = -1;
  
  private static Image j;
  
  private static int c = 1;
  
  private static int d = 2;
  
  private static int e = 8;
  
  private static int f = 4;
  
  public static int a = c | d | e | f;
  
  public static Image a() {
    return (a != null) ? a : (a = gz.a("thumb_135.png"));
  }
  
  public static Image b() {
    return (b != null) ? b : (b = gz.a("community_100.png"));
  }
  
  public static Image c() {
    return (d != null) ? d : (d = gz.a("camera_100.png"));
  }
  
  public static Image d() {
    return (c != null) ? c : (c = gz.a("deactivated_100.png"));
  }
  
  public static Image e() {
    return (e != null) ? e : (e = gz.a("im_multichat_100.png"));
  }
  
  public static Image a(String paramString, boolean paramBoolean) {
    // Byte code:
    //   0: aload_0
    //   1: ifnonnull -> 6
    //   4: aconst_null
    //   5: areturn
    //   6: new java/lang/StringBuffer
    //   9: dup
    //   10: invokespecial <init> : ()V
    //   13: ldc 'lii'
    //   15: invokevirtual append : (Ljava/lang/String;)Ljava/lang/StringBuffer;
    //   18: iload_1
    //   19: ifeq -> 27
    //   22: bipush #98
    //   24: goto -> 29
    //   27: bipush #115
    //   29: invokevirtual append : (C)Ljava/lang/StringBuffer;
    //   32: ldc '_'
    //   34: invokevirtual append : (Ljava/lang/String;)Ljava/lang/StringBuffer;
    //   37: aload_0
    //   38: invokevirtual append : (Ljava/lang/String;)Ljava/lang/StringBuffer;
    //   41: invokevirtual toString : ()Ljava/lang/String;
    //   44: astore_2
    //   45: getstatic kp.a : Ljava/util/Hashtable;
    //   48: aload_2
    //   49: invokevirtual get : (Ljava/lang/Object;)Ljava/lang/Object;
    //   52: checkcast javax/microedition/lcdui/Image
    //   55: dup
    //   56: astore_3
    //   57: ifnull -> 62
    //   60: aload_3
    //   61: areturn
    //   62: aload_0
    //   63: invokestatic a : (Ljava/lang/String;)Ljavax/microedition/lcdui/Image;
    //   66: iload_1
    //   67: ifeq -> 76
    //   70: getstatic hx.a : I
    //   73: goto -> 79
    //   76: getstatic hx.b : I
    //   79: invokestatic a : (Ljavax/microedition/lcdui/Image;I)Ljavax/microedition/lcdui/Image;
    //   82: dup
    //   83: astore_3
    //   84: ifnull -> 96
    //   87: getstatic kp.a : Ljava/util/Hashtable;
    //   90: aload_2
    //   91: aload_3
    //   92: invokevirtual put : (Ljava/lang/Object;Ljava/lang/Object;)Ljava/lang/Object;
    //   95: pop
    //   96: aload_3
    //   97: areturn
  }
  
  public static Image f() {
    if (j == null)
      j = a(gz.a("4dN.png"), (((gz)gz.a).e != null) ? 36 : 24); 
    return j;
  }
  
  public static Image a(int paramInt, boolean paramBoolean) {
    int i;
    if ((i = paramBoolean ? b[paramInt - 1] : a[paramInt - 1]) != null)
      return i; 
    if (paramBoolean) {
      b[paramInt - 1] = a(gz.a(paramInt + "d" + "s.png"), (((gz)gz.a).e != null) ? 36 : 24);
      return a(gz.a(paramInt + "d" + "s.png"), (((gz)gz.a).e != null) ? 36 : 24);
    } 
    a[paramInt - 1] = a(gz.a(paramInt + "d" + ".png"), (((gz)gz.a).e != null) ? 36 : 24);
    return a(gz.a(paramInt + "d" + ".png"), (((gz)gz.a).e != null) ? 36 : 24);
  }
  
  public static void a() {
    // Byte code:
    //   0: getstatic kp.a : Ljava/util/Hashtable;
    //   3: invokevirtual clear : ()V
    //   6: bipush #6
    //   8: anewarray javax/microedition/lcdui/Image
    //   11: putstatic kp.a : [Ljavax/microedition/lcdui/Image;
    //   14: bipush #6
    //   16: anewarray javax/microedition/lcdui/Image
    //   19: putstatic kp.b : [Ljavax/microedition/lcdui/Image;
    //   22: aconst_null
    //   23: putstatic kp.g : Ljavax/microedition/lcdui/Image;
    //   26: aconst_null
    //   27: putstatic kp.f : Ljavax/microedition/lcdui/Image;
    //   30: aconst_null
    //   31: putstatic kp.i : Ljavax/microedition/lcdui/Image;
    //   34: aconst_null
    //   35: putstatic kp.h : Ljavax/microedition/lcdui/Image;
    //   38: aconst_null
    //   39: putstatic kp.j : Ljavax/microedition/lcdui/Image;
    //   42: aconst_null
    //   43: putstatic kp.a : Ljavax/microedition/lcdui/Image;
    //   46: aconst_null
    //   47: putstatic kp.b : Ljavax/microedition/lcdui/Image;
    //   50: aconst_null
    //   51: putstatic kp.c : Ljavax/microedition/lcdui/Image;
    //   54: aconst_null
    //   55: putstatic kp.d : Ljavax/microedition/lcdui/Image;
    //   58: aconst_null
    //   59: putstatic kp.e : Ljavax/microedition/lcdui/Image;
    //   62: invokestatic gc : ()V
    //   65: return
  }
  
  public static Image a(boolean paramBoolean) {
    if (paramBoolean) {
      if (h != null)
        return h; 
      Graphics graphics1;
      (graphics1 = (h = Image.createImage(gz.a.getWidth(), ((gz)gz.a).e)).getGraphics()).setColor(1315860);
      graphics1.drawLine(0, ((gz)gz.a).e - 1, gz.a.getWidth(), ((gz)gz.a).e - 1);
      c(graphics1, 0, 0, gz.a.getWidth(), ((gz)gz.a).e - 1, 2236710, 4539465);
      return h;
    } 
    if (i != null)
      return i; 
    Graphics graphics;
    (graphics = (i = Image.createImage(gz.a.getWidth(), ((gz)gz.a).e)).getGraphics()).setColor(1315860);
    graphics.drawLine(0, 0, gz.a.getWidth(), 0);
    c(graphics, 0, 1, gz.a.getWidth(), ((gz)gz.a).e - 1, 4539465, 2236710);
    return i;
  }
  
  public static Image g() {
    if (g != null)
      return g; 
    Graphics graphics;
    c(graphics = (g = Image.createImage(gz.a.getWidth(), ((gz)gz.a).a)).getGraphics(), 0, 0, gz.a.getWidth(), ((gz)gz.a).a, 4539465, 2236710);
    graphics.setColor(1315860);
    graphics.drawLine(0, gz.a.a() ? 0 : ((gz)gz.a).a, gz.a.getWidth(), gz.a.a() ? 0 : ((gz)gz.a).a);
    return g;
  }
  
  public static Image a(boolean paramBoolean1, boolean paramBoolean2) {
    // Byte code:
    //   0: new java/lang/StringBuffer
    //   3: dup
    //   4: invokespecial <init> : ()V
    //   7: ldc 'ch'
    //   9: invokevirtual append : (Ljava/lang/String;)Ljava/lang/StringBuffer;
    //   12: iload_0
    //   13: ifeq -> 20
    //   16: iconst_1
    //   17: goto -> 21
    //   20: iconst_0
    //   21: invokevirtual append : (I)Ljava/lang/StringBuffer;
    //   24: ldc 'x'
    //   26: invokevirtual append : (Ljava/lang/String;)Ljava/lang/StringBuffer;
    //   29: iload_1
    //   30: ifeq -> 37
    //   33: iconst_1
    //   34: goto -> 38
    //   37: iconst_0
    //   38: invokevirtual append : (I)Ljava/lang/StringBuffer;
    //   41: ldc 'x'
    //   43: invokevirtual append : (Ljava/lang/String;)Ljava/lang/StringBuffer;
    //   46: iconst_0
    //   47: invokevirtual append : (I)Ljava/lang/StringBuffer;
    //   50: invokevirtual toString : ()Ljava/lang/String;
    //   53: astore_2
    //   54: getstatic kp.a : Ljava/util/Hashtable;
    //   57: aload_2
    //   58: invokevirtual get : (Ljava/lang/Object;)Ljava/lang/Object;
    //   61: checkcast javax/microedition/lcdui/Image
    //   64: dup
    //   65: astore_3
    //   66: ifnull -> 71
    //   69: aload_3
    //   70: areturn
    //   71: new java/lang/StringBuffer
    //   74: dup
    //   75: invokespecial <init> : ()V
    //   78: new java/lang/StringBuffer
    //   81: dup
    //   82: invokespecial <init> : ()V
    //   85: ldc 'check'
    //   87: invokevirtual append : (Ljava/lang/String;)Ljava/lang/StringBuffer;
    //   90: iload_0
    //   91: ifeq -> 99
    //   94: ldc 'press'
    //   96: goto -> 101
    //   99: ldc ''
    //   101: invokevirtual append : (Ljava/lang/String;)Ljava/lang/StringBuffer;
    //   104: iload_1
    //   105: ifeq -> 113
    //   108: ldc 'mark'
    //   110: goto -> 115
    //   113: ldc ''
    //   115: invokevirtual append : (Ljava/lang/String;)Ljava/lang/StringBuffer;
    //   118: invokevirtual toString : ()Ljava/lang/String;
    //   121: invokevirtual append : (Ljava/lang/String;)Ljava/lang/StringBuffer;
    //   124: ldc '.png'
    //   126: invokevirtual append : (Ljava/lang/String;)Ljava/lang/StringBuffer;
    //   129: invokevirtual toString : ()Ljava/lang/String;
    //   132: invokestatic a : (Ljava/lang/String;)Ljavax/microedition/lcdui/Image;
    //   135: getstatic gz.a : Lgz;
    //   138: getfield a : Ljavax/microedition/lcdui/Font;
    //   141: invokevirtual getHeight : ()I
    //   144: bipush #8
    //   146: iadd
    //   147: invokestatic a : (Ljavax/microedition/lcdui/Image;I)Ljavax/microedition/lcdui/Image;
    //   150: astore_3
    //   151: getstatic kp.a : Ljava/util/Hashtable;
    //   154: aload_2
    //   155: aload_3
    //   156: invokevirtual put : (Ljava/lang/Object;Ljava/lang/Object;)Ljava/lang/Object;
    //   159: pop
    //   160: aload_3
    //   161: areturn
  }
  
  public static Image h() {
    if (f != null)
      return f; 
    Graphics graphics;
    c(graphics = (f = Image.createImage(((gz)gz.a).b, ((gz)gz.a).a)).getGraphics(), 0, 0, ((gz)gz.a).b, ((gz)gz.a).a, 4539465, 2236710);
    graphics.setColor(1315860);
    graphics.drawLine(0, gz.a.a() ? 0 : ((gz)gz.a).a, ((gz)gz.a).b, gz.a.a() ? 0 : ((gz)gz.a).a);
    Image image = gz.a("dsel" + ((((gz)gz.a).e != null) ? "" : "s") + ".png");
    for (byte b = 0; b < ((gz)gz.a).b; b += 10)
      graphics.drawRegion(image, 0, 0, 10, (((gz)gz.a).e != null) ? 56 : 36, gz.a.a() ? 3 : 0, b, 0, 20); 
    return f;
  }
  
  public static Image a(int paramInt1, int paramInt2) {
    if (paramInt1 <= 0)
      paramInt1 = 1; 
    int i = paramInt1 * ((gz)gz.a).i;
    if (c == null || b != i) {
      c = new Image[7];
      b = i;
    } 
    if (c[paramInt2] == null) {
      i = 0xFF000000 & paramInt2 * 255 / 10 << 24;
      int[] arrayOfInt = new int[b];
      for (byte b = 0; b < arrayOfInt.length; b++)
        arrayOfInt[b] = i; 
      c[paramInt2] = a(((gz)gz.a).i / 2, Image.createRGBImage(arrayOfInt, ((gz)gz.a).i, paramInt1, true), a, paramInt2 * 10);
    } 
    return c[paramInt2];
  }
  
  public static Image a(int paramInt1, int paramInt2, boolean paramBoolean) {
    // Byte code:
    //   0: new java/lang/StringBuffer
    //   3: dup
    //   4: invokespecial <init> : ()V
    //   7: ldc 'b'
    //   9: invokevirtual append : (Ljava/lang/String;)Ljava/lang/StringBuffer;
    //   12: iload_0
    //   13: invokevirtual append : (I)Ljava/lang/StringBuffer;
    //   16: ldc 'x'
    //   18: invokevirtual append : (Ljava/lang/String;)Ljava/lang/StringBuffer;
    //   21: iload_1
    //   22: invokevirtual append : (I)Ljava/lang/StringBuffer;
    //   25: ldc 'x'
    //   27: invokevirtual append : (Ljava/lang/String;)Ljava/lang/StringBuffer;
    //   30: iload_2
    //   31: ifeq -> 38
    //   34: iconst_1
    //   35: goto -> 39
    //   38: iconst_0
    //   39: invokevirtual append : (I)Ljava/lang/StringBuffer;
    //   42: invokevirtual toString : ()Ljava/lang/String;
    //   45: astore_3
    //   46: getstatic kp.a : Ljava/util/Hashtable;
    //   49: aload_3
    //   50: invokevirtual get : (Ljava/lang/Object;)Ljava/lang/Object;
    //   53: checkcast javax/microedition/lcdui/Image
    //   56: dup
    //   57: astore #4
    //   59: ifnull -> 65
    //   62: aload #4
    //   64: areturn
    //   65: iload_0
    //   66: iload_1
    //   67: invokestatic createImage : (II)Ljavax/microedition/lcdui/Image;
    //   70: dup
    //   71: astore #4
    //   73: invokevirtual getGraphics : ()Ljavax/microedition/lcdui/Graphics;
    //   76: dup
    //   77: astore #5
    //   79: iconst_0
    //   80: iconst_0
    //   81: iload_0
    //   82: iload_1
    //   83: iload_1
    //   84: iconst_3
    //   85: idiv
    //   86: iload_2
    //   87: ifeq -> 95
    //   90: ldc 7708140
    //   92: goto -> 97
    //   95: ldc 16053492
    //   97: iload_2
    //   98: ifeq -> 106
    //   101: ldc 4681404
    //   103: goto -> 108
    //   106: ldc 12895428
    //   108: getstatic kp.a : I
    //   111: invokestatic a : (Ljavax/microedition/lcdui/Graphics;IIIIIIII)V
    //   114: aload #5
    //   116: ldc 11842740
    //   118: invokevirtual setColor : (I)V
    //   121: aload #5
    //   123: iconst_0
    //   124: iconst_0
    //   125: iload_0
    //   126: iload_1
    //   127: iload_1
    //   128: iconst_3
    //   129: idiv
    //   130: getstatic kp.a : I
    //   133: invokestatic b : (Ljavax/microedition/lcdui/Graphics;IIIIII)V
    //   136: getstatic kp.a : Ljava/util/Hashtable;
    //   139: aload_3
    //   140: aload #4
    //   142: invokevirtual put : (Ljava/lang/Object;Ljava/lang/Object;)Ljava/lang/Object;
    //   145: pop
    //   146: aload #4
    //   148: areturn
  }
  
  private static Image a(int paramInt1, int paramInt2, int paramInt3, int paramInt4, int paramInt5) {
    Image image;
    Graphics graphics;
    (graphics = (image = Image.createImage(paramInt1, paramInt2)).getGraphics()).setColor(paramInt3);
    graphics.fillRect(0, 0, paramInt1, paramInt2);
    return a(paramInt4, image, paramInt5);
  }
  
  public static void a(Graphics paramGraphics, int paramInt1, int paramInt2, int paramInt3, int paramInt4, int paramInt5, int paramInt6) {
    paramGraphics.drawImage(a(paramInt3, paramInt4, paramGraphics.getColor(), paramInt5, paramInt6), paramInt1, paramInt2, 20);
  }
  
  private static void a(Graphics paramGraphics, int paramInt1, int paramInt2, int paramInt3, int paramInt4, int paramInt5, int paramInt6, int paramInt7, int paramInt8) {
    Image image;
    c((image = Image.createImage(paramInt3, paramInt4)).getGraphics(), 0, 0, paramInt3, paramInt4, paramInt6, paramInt7);
    paramGraphics.drawImage(a(paramInt5, image, paramInt8), paramInt1, paramInt2, 20);
  }
  
  public static void b(Graphics paramGraphics, int paramInt1, int paramInt2, int paramInt3, int paramInt4, int paramInt5, int paramInt6) {
    int j = paramGraphics.getColor();
    int i;
    if ((i = paramInt5) <= 0)
      i = 1; 
    int[] arrayOfInt = new int[i * i];
    j &= 0xFFFFFF;
    int k = i << 1;
    int m = i * i;
    for (byte b2 = 0; b2 < i; b2++) {
      int n = b2 * i;
      int i1;
      int i2 = (i1 = (i - b2) * (i - b2)) << 2;
      int i3 = (k - 1 - (b2 << 1)) * (k - 1 - (b2 << 1));
      for (byte b = 0; b < i; b++) {
        int i4;
        int i5 = (i4 = (i - b) * (i - b)) << 2;
        int i6 = (k - 1 - (b << 1)) * (k - 1 - (b << 1));
        i4 = ((Math.abs(i1 + i4 - m) <= i) ? 63 : 0) + ((Math.abs(i2 / 4 + i6 / 4 - m) <= i) ? 64 : 0) + ((Math.abs(i3 / 4 + i5 / 4 - m) <= i) ? 64 : 0) + ((Math.abs(i3 / 4 + i6 / 4 - m) <= i) ? 64 : 0);
        arrayOfInt[b + n] = i4 << 24 | j;
      } 
    } 
    Image image = Image.createRGBImage(arrayOfInt, i, i, true);
    j = ((paramInt6 & c) == c) ? paramInt5 : 0;
    byte b1 = ((paramInt6 & d) == d) ? paramInt5 : 0;
    k = ((paramInt6 & e) == e) ? paramInt5 : 0;
    paramInt6 = ((paramInt6 & f) == f) ? paramInt5 : 0;
    if (j != 0)
      paramGraphics.drawImage(image, paramInt1, paramInt2, 0); 
    if (b1)
      paramGraphics.drawRegion(image, 0, 0, paramInt5, paramInt5, 5, paramInt1 + paramInt3 - b1, paramInt2, 0); 
    if (paramInt6 != 0)
      paramGraphics.drawRegion(image, 0, 0, paramInt5, paramInt5, 3, paramInt1 + paramInt3 - paramInt6, paramInt2 + paramInt4 - paramInt6, 0); 
    if (k != 0)
      paramGraphics.drawRegion(image, 0, 0, paramInt5, paramInt5, 6, paramInt1, paramInt2 + paramInt4 - k, 0); 
    if (paramInt4 - j - k > 0)
      paramGraphics.drawLine(paramInt1, paramInt2 + j, paramInt1, paramInt2 + paramInt4 - k - 1); 
    if (paramInt4 - b1 - paramInt6 > 0)
      paramGraphics.drawLine(paramInt1 + paramInt3 - 1, paramInt2 + b1, paramInt1 + paramInt3 - 1, paramInt2 + paramInt4 - paramInt6 - 1); 
    if (paramInt3 - j - b1 > 0)
      paramGraphics.drawLine(paramInt1 + j, paramInt2, paramInt1 + paramInt3 - b1, paramInt2); 
    if (paramInt3 - k - paramInt6 > 0)
      paramGraphics.drawLine(paramInt1 + k, paramInt2 + paramInt4 - 1, paramInt1 + paramInt3 - paramInt6, paramInt2 + paramInt4 - 1); 
  }
  
  public static Image a(int paramInt, Image paramImage) {
    return a(paramInt, paramImage, a);
  }
  
  private static Image a(int paramInt1, Image paramImage, int paramInt2) {
    return a(paramInt1, paramImage, paramInt2, 100);
  }
  
  private static Image a(int paramInt1, Image paramImage, int paramInt2, int paramInt3) {
    if (paramInt1 <= 0)
      return paramImage; 
    if (paramImage == null)
      return null; 
    int j = paramImage.getWidth();
    int k = paramImage.getHeight();
    int[] arrayOfInt = new int[j * k];
    paramImage.getRGB(arrayOfInt, 0, j, 0, 0, j, k);
    int i = Math.max(paramInt2 & 0x1, paramInt2 >> 1 & 0x1);
    int m = Math.max(paramInt2 >> 2 & 0x1, paramInt2 >> 2 & 0x1);
    i = (i <= 0 || m <= 0) ? 1 : 0;
    m = ((paramInt2 & c) == c) ? 1 : 0;
    boolean bool1 = ((paramInt2 & d) == d) ? true : false;
    boolean bool2 = ((paramInt2 & e) == e) ? true : false;
    paramInt2 = ((paramInt2 & f) == f) ? 1 : 0;
    if (i == 0) {
      if (paramInt1 > k / 2 || paramInt1 > j / 2)
        paramInt1 = j / 2; 
      if (paramInt1 > k / 2 || paramInt1 > j / 2)
        paramInt1 = k / 2; 
    } else {
      if (paramInt1 > k || paramInt1 > j)
        paramInt1 = j; 
      if (paramInt1 > k || paramInt1 > j)
        paramInt1 = k; 
    } 
    i = paramInt1 << 1;
    int n;
    int i1 = (n = paramInt1 * paramInt1) << 2;
    for (int i2 = 0; i2 < paramInt1; i2++) {
      int i3;
      int i4 = (i3 = (paramInt1 - i2) * (paramInt1 - i2)) << 2;
      int i5 = (i - 1 - (i2 << 1)) * (i - 1 - (i2 << 1));
      for (int i6 = 0; i6 < paramInt1; i6++) {
        int i7;
        int i8 = (i7 = (paramInt1 - i6) * (paramInt1 - i6)) << 2;
        int i9 = (i - 1 - (i6 << 1)) * (i - 1 - (i6 << 1));
        i7 = ((i7 + i3 >= n) ? 63 : 0) + ((i8 + i5 >= i1) ? 64 : 0) + ((i9 + i4 >= i1) ? 64 : 0) + ((i9 + i5 >= i1) ? 64 : 0);
        i7 = (255 - i7) * paramInt3 / 100;
        i8 = i6;
        i9 = i2;
        if (m != 0) {
          arrayOfInt[i2 * j + i6] = arrayOfInt[i2 * j + i6] & 0xFFFFFF;
          arrayOfInt[i2 * j + i6] = i7 << 24 | arrayOfInt[i2 * j + i6] & 0xFFFFFF;
        } 
        i6 = j - i6 - 1;
        if (bool1) {
          arrayOfInt[i2 * j + i6] = arrayOfInt[i2 * j + i6] & 0xFFFFFF;
          arrayOfInt[i2 * j + i6] = i7 << 24 | arrayOfInt[i2 * j + i6] & 0xFFFFFF;
        } 
        i2 = k - i2 - 1;
        if (paramInt2 != 0) {
          arrayOfInt[i2 * j + i6] = arrayOfInt[i2 * j + i6] & 0xFFFFFF;
          arrayOfInt[i2 * j + i6] = i7 << 24 | arrayOfInt[i2 * j + i6] & 0xFFFFFF;
        } 
        i6 = i8;
        if (bool2) {
          arrayOfInt[i2 * j + i6] = arrayOfInt[i2 * j + i6] & 0xFFFFFF;
          arrayOfInt[i2 * j + i6] = i7 << 24 | arrayOfInt[i2 * j + i6] & 0xFFFFFF;
        } 
        i2 = i9;
      } 
    } 
    return Image.createRGBImage(arrayOfInt, j, k, true);
  }
  
  public static void a(Graphics paramGraphics, int paramInt1, int paramInt2, int paramInt3, int paramInt4, boolean paramBoolean) {
    // Byte code:
    //   0: new java/lang/StringBuffer
    //   3: dup
    //   4: invokespecial <init> : ()V
    //   7: ldc 'tf'
    //   9: invokevirtual append : (Ljava/lang/String;)Ljava/lang/StringBuffer;
    //   12: iload_3
    //   13: invokevirtual append : (I)Ljava/lang/StringBuffer;
    //   16: ldc 'x'
    //   18: invokevirtual append : (Ljava/lang/String;)Ljava/lang/StringBuffer;
    //   21: iload #4
    //   23: invokevirtual append : (I)Ljava/lang/StringBuffer;
    //   26: ldc 'x'
    //   28: invokevirtual append : (Ljava/lang/String;)Ljava/lang/StringBuffer;
    //   31: invokevirtual toString : ()Ljava/lang/String;
    //   34: astore #6
    //   36: getstatic kp.a : Ljava/util/Hashtable;
    //   39: aload #6
    //   41: invokevirtual get : (Ljava/lang/Object;)Ljava/lang/Object;
    //   44: checkcast javax/microedition/lcdui/Image
    //   47: dup
    //   48: astore #7
    //   50: ifnonnull -> 81
    //   53: iload_3
    //   54: iload #4
    //   56: ldc 16053492
    //   58: iload #4
    //   60: iconst_3
    //   61: idiv
    //   62: getstatic kp.a : I
    //   65: invokestatic a : (IIIII)Ljavax/microedition/lcdui/Image;
    //   68: astore #7
    //   70: getstatic kp.a : Ljava/util/Hashtable;
    //   73: aload #6
    //   75: aload #7
    //   77: invokevirtual put : (Ljava/lang/Object;Ljava/lang/Object;)Ljava/lang/Object;
    //   80: pop
    //   81: aload_0
    //   82: aload #7
    //   84: iload_1
    //   85: iload_2
    //   86: iconst_0
    //   87: invokevirtual drawImage : (Ljavax/microedition/lcdui/Image;III)V
    //   90: aload_0
    //   91: iload #5
    //   93: ifeq -> 101
    //   96: ldc 4681404
    //   98: goto -> 103
    //   101: ldc 11842740
    //   103: invokevirtual setColor : (I)V
    //   106: aload_0
    //   107: iload_1
    //   108: iload_2
    //   109: iload_3
    //   110: iload #4
    //   112: iload #4
    //   114: iconst_3
    //   115: idiv
    //   116: getstatic kp.a : I
    //   119: invokestatic b : (Ljavax/microedition/lcdui/Graphics;IIIIII)V
    //   122: return
  }
  
  public static void c(Graphics paramGraphics, int paramInt1, int paramInt2, int paramInt3, int paramInt4, int paramInt5, int paramInt6) {
    if (paramInt3 == 0 || paramInt4 == 0)
      return; 
    if (paramInt5 == paramInt6 || !v.a.d) {
      if (!v.a.d) {
        paramGraphics.setColor(((paramInt5 & 0xFF00FF) + (paramInt6 & 0xFF00FF) & 0x1FE01FE | (paramInt5 & 0xFF00) + (paramInt6 & 0xFF00) & 0x1FE00) >> 1);
      } else {
        paramGraphics.setColor(paramInt5);
      } 
      paramGraphics.fillRect(paramInt1, paramInt2, paramInt3, paramInt4);
      return;
    } 
    int i = paramInt5 >> 16 & 0xFF;
    int j = paramInt5 >> 8 & 0xFF;
    paramInt5 &= 0xFF;
    int k = paramInt6 >> 16 & 0xFF;
    int m = paramInt6 >> 8 & 0xFF;
    paramInt6 &= 0xFF;
    for (byte b = 0; b < paramInt4; b++) {
      paramGraphics.setColor((k - i) * b / paramInt4 + i, (m - j) * b / paramInt4 + j, (paramInt6 - paramInt5) * b / paramInt4 + paramInt5);
      paramGraphics.drawLine(paramInt1, paramInt2 + b, paramInt1 + paramInt3 - 1, paramInt2 + b);
    } 
  }
  
  public static Image a(Image paramImage, int paramInt) {
    if (paramImage == null)
      return null; 
    if (paramInt >= paramImage.getHeight())
      return paramImage; 
    if (paramInt <= 0)
      return Image.createImage(1, 1); 
    int i = paramImage.getWidth();
    int j = paramImage.getHeight();
    int k = paramImage.getWidth() * paramInt / paramImage.getHeight();
    int[] arrayOfInt2 = new int[i * j];
    paramImage.getRGB(arrayOfInt2, 0, i, 0, 0, i, j);
    int[] arrayOfInt1 = new int[k * j];
    int[] arrayOfInt3 = new int[k * paramInt];
    if (k < i) {
      for (byte b = 0; b < j; b++) {
        int m = b * i;
        int n = b * k;
        int i1 = 0;
        int i2 = 0;
        int i3 = 0;
        int i4 = 0;
        int i5 = 0;
        for (byte b1 = 0; b1 < k; b1++) {
          int i6 = i;
          int i7 = 0;
          int i8 = 0;
          int i9 = 0;
          int i10 = 0;
          if (i1) {
            i7 = i2 * i1;
            i8 = i3 * i1;
            i9 = i4 * i1;
            i10 = i5 * i1;
            i6 = i - i1;
          } 
          while (i6 > 0) {
            i5 = arrayOfInt2[m] >>> 24;
            i2 = arrayOfInt2[m] >> 16 & 0xFF;
            i3 = arrayOfInt2[m] >> 8 & 0xFF;
            i4 = arrayOfInt2[m++] & 0xFF;
            if (i6 > k) {
              i7 += i2 * k;
              i8 += i3 * k;
              i9 += i4 * k;
              i10 += i5 * k;
            } else {
              i7 += i2 * i6;
              i8 += i3 * i6;
              i9 += i4 * i6;
              i10 += i5 * i6;
              i1 = k - i6;
              arrayOfInt1[n++] = i7 / i << 16 | i8 / i << 8 | i9 / i | i10 / i << 24;
            } 
            i6 -= k;
          } 
        } 
      } 
    } else {
      for (byte b = 0; b < j; b++) {
        int n = b * i;
        int m = b * k;
        int i1 = 0;
        int i2 = 0;
        int i3 = 0;
        int i4 = 0;
        int i5 = 0;
        for (byte b1 = 0; b1 < k; b1++) {
          int i6 = 0;
          int i7 = 0;
          int i8 = 0;
          int i9 = 0;
          if (i1 >= i) {
            i6 = i2 * i;
            i7 = i3 * i;
            i8 = i4 * i;
            i9 = i5 * i;
            i1 -= i;
          } else {
            if (i1 != 0) {
              i6 = i2 * i1;
              i7 = i3 * i1;
              i8 = i4 * i1;
              i9 = i5 * i1;
            } 
            i5 = arrayOfInt2[n] >>> 24;
            i2 = arrayOfInt2[n] >> 16 & 0xFF;
            i3 = arrayOfInt2[n] >> 8 & 0xFF;
            i4 = arrayOfInt2[n++] & 0xFF;
            int i10 = i - i1;
            i6 += i2 * i10;
            i7 += i3 * i10;
            i8 += i4 * i10;
            i9 += i5 * i10;
            i1 = k - i10;
          } 
          arrayOfInt1[m++] = i6 / i << 16 | i7 / i << 8 | i8 / i | i9 / i << 24;
        } 
      } 
    } 
    if (paramInt < j) {
      for (byte b = 0; b < k; b++) {
        int m = b;
        int n = b;
        int i1 = 0;
        int i2 = 0;
        int i3 = 0;
        int i4 = 0;
        int i5 = 0;
        for (byte b1 = 0; b1 < paramInt; b1++) {
          int i6 = j;
          int i7 = 0;
          int i8 = 0;
          int i9 = 0;
          int i10 = 0;
          if (i1) {
            i7 = i2 * i1;
            i8 = i3 * i1;
            i9 = i4 * i1;
            i10 = i5 * i1;
            i6 = j - i1;
          } 
          while (i6 > 0) {
            i5 = arrayOfInt1[m] >>> 24;
            i2 = arrayOfInt1[m] >> 16 & 0xFF;
            i3 = arrayOfInt1[m] >> 8 & 0xFF;
            i4 = arrayOfInt1[m] & 0xFF;
            m += k;
            if (i6 > paramInt) {
              i7 += i2 * paramInt;
              i8 += i3 * paramInt;
              i9 += i4 * paramInt;
              i10 += i5 * paramInt;
            } else {
              i7 += i2 * i6;
              i8 += i3 * i6;
              i9 += i4 * i6;
              i10 += i5 * i6;
              i1 = paramInt - i6;
              if (i10 != 0) {
                arrayOfInt3[n] = i7 / j << 16 | i8 / j << 8 | i9 / j | i10 / j << 24;
              } else {
                arrayOfInt3[n] = 0;
              } 
              n += k;
            } 
            i6 -= paramInt;
          } 
        } 
      } 
    } else {
      for (byte b = 0; b < k; b++) {
        int n = b;
        int m = b;
        int i1 = 0;
        int i2 = 0;
        int i3 = 0;
        int i4 = 0;
        int i5 = 0;
        for (byte b1 = 0; b1 < paramInt; b1++) {
          int i6 = 0;
          int i7 = 0;
          int i8 = 0;
          int i9 = 0;
          if (i1 >= j) {
            i6 = i2 * j;
            i7 = i3 * j;
            i8 = i4 * j;
            i9 = i5 * j;
            i1 -= j;
          } else {
            if (i1 != 0) {
              i6 = i2 * i1;
              i7 = i3 * i1;
              i8 = i4 * i1;
              i9 = i5 * i1;
            } 
            i5 = arrayOfInt1[n] >>> 24;
            i2 = arrayOfInt1[n] >> 16 & 0xFF;
            i3 = arrayOfInt1[n] >> 8 & 0xFF;
            i4 = arrayOfInt1[n] & 0xFF;
            n += k;
            int i10 = j - i1;
            i6 += i2 * i10;
            i7 += i3 * i10;
            i8 += i4 * i10;
            i9 += i5 * i10;
            i1 = paramInt - i10;
          } 
          if (i9 != 0) {
            arrayOfInt3[m] = i6 / j << 16 | i7 / j << 8 | i8 / j | i9 / j << 24;
          } else {
            arrayOfInt3[m] = 0;
          } 
          m += k;
        } 
      } 
    } 
    return Image.createRGBImage(arrayOfInt3, k, paramInt, true);
  }
  
  public static Image b(int paramInt1, int paramInt2, boolean paramBoolean) {
    // Byte code:
    //   0: new java/lang/StringBuffer
    //   3: dup
    //   4: invokespecial <init> : ()V
    //   7: ldc 'li'
    //   9: invokevirtual append : (Ljava/lang/String;)Ljava/lang/StringBuffer;
    //   12: iload_0
    //   13: invokevirtual append : (I)Ljava/lang/StringBuffer;
    //   16: ldc 'x'
    //   18: invokevirtual append : (Ljava/lang/String;)Ljava/lang/StringBuffer;
    //   21: iload_1
    //   22: invokevirtual append : (I)Ljava/lang/StringBuffer;
    //   25: iload_2
    //   26: ifeq -> 33
    //   29: iconst_1
    //   30: goto -> 34
    //   33: iconst_0
    //   34: invokevirtual append : (I)Ljava/lang/StringBuffer;
    //   37: invokevirtual toString : ()Ljava/lang/String;
    //   40: astore_3
    //   41: getstatic kp.a : Ljava/util/Hashtable;
    //   44: aload_3
    //   45: invokevirtual get : (Ljava/lang/Object;)Ljava/lang/Object;
    //   48: checkcast javax/microedition/lcdui/Image
    //   51: dup
    //   52: astore #4
    //   54: ifnull -> 60
    //   57: aload #4
    //   59: areturn
    //   60: iload_0
    //   61: iload_1
    //   62: invokestatic createImage : (II)Ljavax/microedition/lcdui/Image;
    //   65: dup
    //   66: astore #4
    //   68: invokevirtual getGraphics : ()Ljavax/microedition/lcdui/Graphics;
    //   71: iconst_0
    //   72: iconst_0
    //   73: iload_0
    //   74: iload_1
    //   75: iload_2
    //   76: ifeq -> 84
    //   79: ldc 15496565
    //   81: goto -> 86
    //   84: ldc 7708140
    //   86: iload_2
    //   87: ifeq -> 95
    //   90: ldc 12339015
    //   92: goto -> 97
    //   95: ldc 4681404
    //   97: invokestatic c : (Ljavax/microedition/lcdui/Graphics;IIIIII)V
    //   100: getstatic kp.a : Ljava/util/Hashtable;
    //   103: aload_3
    //   104: aload #4
    //   106: invokevirtual put : (Ljava/lang/Object;Ljava/lang/Object;)Ljava/lang/Object;
    //   109: pop
    //   110: aload #4
    //   112: areturn
  }
  
  public static Image b(boolean paramBoolean) {
    // Byte code:
    //   0: new java/lang/StringBuffer
    //   3: dup
    //   4: invokespecial <init> : ()V
    //   7: ldc 'gt'
    //   9: invokevirtual append : (Ljava/lang/String;)Ljava/lang/StringBuffer;
    //   12: iload_0
    //   13: ifeq -> 21
    //   16: ldc '1'
    //   18: goto -> 23
    //   21: ldc '0'
    //   23: invokevirtual append : (Ljava/lang/String;)Ljava/lang/StringBuffer;
    //   26: invokevirtual toString : ()Ljava/lang/String;
    //   29: astore_1
    //   30: getstatic kp.a : Ljava/util/Hashtable;
    //   33: aload_1
    //   34: invokevirtual get : (Ljava/lang/Object;)Ljava/lang/Object;
    //   37: checkcast javax/microedition/lcdui/Image
    //   40: dup
    //   41: astore_2
    //   42: ifnull -> 47
    //   45: aload_2
    //   46: areturn
    //   47: new java/lang/StringBuffer
    //   50: dup
    //   51: invokespecial <init> : ()V
    //   54: ldc 'goto'
    //   56: invokevirtual append : (Ljava/lang/String;)Ljava/lang/StringBuffer;
    //   59: iload_0
    //   60: ifeq -> 68
    //   63: ldc 's'
    //   65: goto -> 70
    //   68: ldc ''
    //   70: invokevirtual append : (Ljava/lang/String;)Ljava/lang/StringBuffer;
    //   73: ldc '.png'
    //   75: invokevirtual append : (Ljava/lang/String;)Ljava/lang/StringBuffer;
    //   78: invokevirtual toString : ()Ljava/lang/String;
    //   81: invokestatic a : (Ljava/lang/String;)Ljavax/microedition/lcdui/Image;
    //   84: getstatic gz.a : Lgz;
    //   87: getfield a : Ljavax/microedition/lcdui/Font;
    //   90: invokevirtual getHeight : ()I
    //   93: bipush #8
    //   95: iadd
    //   96: invokestatic a : (Ljavax/microedition/lcdui/Image;I)Ljavax/microedition/lcdui/Image;
    //   99: astore_2
    //   100: getstatic kp.a : Ljava/util/Hashtable;
    //   103: aload_1
    //   104: aload_2
    //   105: invokevirtual put : (Ljava/lang/Object;Ljava/lang/Object;)Ljava/lang/Object;
    //   108: pop
    //   109: aload_2
    //   110: areturn
  }
  
  public static Image b(int paramInt, boolean paramBoolean) {
    // Byte code:
    //   0: new java/lang/StringBuffer
    //   3: dup
    //   4: invokespecial <init> : ()V
    //   7: ldc 'sli'
    //   9: invokevirtual append : (Ljava/lang/String;)Ljava/lang/StringBuffer;
    //   12: iload_0
    //   13: invokevirtual append : (I)Ljava/lang/StringBuffer;
    //   16: ldc 'x'
    //   18: invokevirtual append : (Ljava/lang/String;)Ljava/lang/StringBuffer;
    //   21: iload_1
    //   22: ifeq -> 30
    //   25: ldc '1'
    //   27: goto -> 32
    //   30: ldc '0'
    //   32: invokevirtual append : (Ljava/lang/String;)Ljava/lang/StringBuffer;
    //   35: invokevirtual toString : ()Ljava/lang/String;
    //   38: astore_2
    //   39: getstatic kp.a : Ljava/util/Hashtable;
    //   42: aload_2
    //   43: invokevirtual get : (Ljava/lang/Object;)Ljava/lang/Object;
    //   46: checkcast javax/microedition/lcdui/Image
    //   49: dup
    //   50: astore_3
    //   51: ifnull -> 56
    //   54: aload_3
    //   55: areturn
    //   56: iload_0
    //   57: iload_0
    //   58: invokestatic createImage : (II)Ljavax/microedition/lcdui/Image;
    //   61: dup
    //   62: astore_3
    //   63: invokevirtual getGraphics : ()Ljavax/microedition/lcdui/Graphics;
    //   66: dup
    //   67: astore #4
    //   69: iconst_0
    //   70: iconst_0
    //   71: iload_0
    //   72: iload_0
    //   73: iload_1
    //   74: ifeq -> 82
    //   77: ldc 7708140
    //   79: goto -> 84
    //   82: ldc 16053492
    //   84: iload_1
    //   85: ifeq -> 93
    //   88: ldc 4681404
    //   90: goto -> 95
    //   93: ldc 12895428
    //   95: invokestatic c : (Ljavax/microedition/lcdui/Graphics;IIIIII)V
    //   98: aload #4
    //   100: ldc 11842740
    //   102: invokevirtual setColor : (I)V
    //   105: aload #4
    //   107: iconst_0
    //   108: iconst_0
    //   109: iload_0
    //   110: iload_0
    //   111: iload_0
    //   112: iconst_2
    //   113: idiv
    //   114: getstatic kp.a : I
    //   117: invokestatic b : (Ljavax/microedition/lcdui/Graphics;IIIIII)V
    //   120: iload_0
    //   121: iconst_2
    //   122: idiv
    //   123: aload_3
    //   124: invokestatic a : (ILjavax/microedition/lcdui/Image;)Ljavax/microedition/lcdui/Image;
    //   127: astore_3
    //   128: getstatic kp.a : Ljava/util/Hashtable;
    //   131: aload_2
    //   132: aload_3
    //   133: invokevirtual put : (Ljava/lang/Object;Ljava/lang/Object;)Ljava/lang/Object;
    //   136: pop
    //   137: aload_3
    //   138: areturn
  }
  
  public static Image a(int paramInt1, boolean paramBoolean1, int paramInt2, boolean paramBoolean2, boolean paramBoolean3, boolean paramBoolean4) {
    // Byte code:
    //   0: new java/lang/StringBuffer
    //   3: dup
    //   4: invokespecial <init> : ()V
    //   7: ldc 'mf'
    //   9: invokevirtual append : (Ljava/lang/String;)Ljava/lang/StringBuffer;
    //   12: iload_0
    //   13: invokevirtual append : (I)Ljava/lang/StringBuffer;
    //   16: ldc 'x'
    //   18: invokevirtual append : (Ljava/lang/String;)Ljava/lang/StringBuffer;
    //   21: iload_1
    //   22: ifeq -> 30
    //   25: ldc '1'
    //   27: goto -> 32
    //   30: ldc '0'
    //   32: invokevirtual append : (Ljava/lang/String;)Ljava/lang/StringBuffer;
    //   35: ldc 'x'
    //   37: invokevirtual append : (Ljava/lang/String;)Ljava/lang/StringBuffer;
    //   40: iload_2
    //   41: invokevirtual append : (I)Ljava/lang/StringBuffer;
    //   44: ldc 'x'
    //   46: invokevirtual append : (Ljava/lang/String;)Ljava/lang/StringBuffer;
    //   49: iload_3
    //   50: ifeq -> 57
    //   53: iconst_1
    //   54: goto -> 58
    //   57: iconst_0
    //   58: invokevirtual append : (I)Ljava/lang/StringBuffer;
    //   61: iload #4
    //   63: ifeq -> 70
    //   66: iconst_1
    //   67: goto -> 71
    //   70: iconst_0
    //   71: invokevirtual append : (I)Ljava/lang/StringBuffer;
    //   74: iload #5
    //   76: ifeq -> 83
    //   79: iconst_1
    //   80: goto -> 84
    //   83: iconst_0
    //   84: invokevirtual append : (I)Ljava/lang/StringBuffer;
    //   87: invokevirtual toString : ()Ljava/lang/String;
    //   90: astore #6
    //   92: getstatic kp.a : Ljava/util/Hashtable;
    //   95: aload #6
    //   97: invokevirtual get : (Ljava/lang/Object;)Ljava/lang/Object;
    //   100: checkcast javax/microedition/lcdui/Image
    //   103: dup
    //   104: astore #7
    //   106: ifnull -> 112
    //   109: aload #7
    //   111: areturn
    //   112: iload_1
    //   113: ifeq -> 122
    //   116: getstatic eb.b : I
    //   119: goto -> 125
    //   122: getstatic eb.c : I
    //   125: istore #8
    //   127: iload_0
    //   128: iload #8
    //   130: invokestatic createImage : (II)Ljavax/microedition/lcdui/Image;
    //   133: dup
    //   134: astore #7
    //   136: invokevirtual getGraphics : ()Ljavax/microedition/lcdui/Graphics;
    //   139: dup
    //   140: astore #9
    //   142: iconst_0
    //   143: iconst_0
    //   144: iload_0
    //   145: iload #8
    //   147: iconst_0
    //   148: ldc 15000804
    //   150: ldc 12895428
    //   152: iconst_0
    //   153: invokestatic a : (Ljavax/microedition/lcdui/Graphics;IIIIIIII)V
    //   156: iload_1
    //   157: ifeq -> 165
    //   160: ldc 'down.png'
    //   162: goto -> 167
    //   165: ldc 'up.png'
    //   167: invokestatic a : (Ljava/lang/String;)Ljavax/microedition/lcdui/Image;
    //   170: getstatic eb.c : I
    //   173: invokestatic a : (Ljavax/microedition/lcdui/Image;I)Ljavax/microedition/lcdui/Image;
    //   176: astore #8
    //   178: aload #9
    //   180: aload #8
    //   182: iload_0
    //   183: iconst_2
    //   184: idiv
    //   185: iconst_0
    //   186: bipush #17
    //   188: invokevirtual drawImage : (Ljavax/microedition/lcdui/Image;III)V
    //   191: aload #9
    //   193: ldc 11842740
    //   195: invokevirtual setColor : (I)V
    //   198: aload #9
    //   200: iconst_0
    //   201: iconst_0
    //   202: iload_0
    //   203: iconst_0
    //   204: invokevirtual drawLine : (IIII)V
    //   207: iload_1
    //   208: ifeq -> 692
    //   211: aload #9
    //   213: ldc 16053492
    //   215: invokevirtual setColor : (I)V
    //   218: aload #9
    //   220: getstatic eb.c : I
    //   223: iconst_2
    //   224: idiv
    //   225: getstatic eb.i : I
    //   228: iadd
    //   229: iconst_1
    //   230: isub
    //   231: getstatic eb.c : I
    //   234: iload_0
    //   235: iconst_2
    //   236: iadd
    //   237: getstatic eb.c : I
    //   240: isub
    //   241: getstatic eb.i : I
    //   244: iconst_1
    //   245: ishl
    //   246: isub
    //   247: getstatic eb.h : I
    //   250: getstatic eb.h : I
    //   253: iconst_3
    //   254: idiv
    //   255: iconst_0
    //   256: invokestatic a : (Ljavax/microedition/lcdui/Graphics;IIIIII)V
    //   259: aload #9
    //   261: ldc 11842740
    //   263: invokevirtual setColor : (I)V
    //   266: aload #9
    //   268: getstatic eb.c : I
    //   271: iconst_2
    //   272: idiv
    //   273: getstatic eb.i : I
    //   276: iadd
    //   277: iconst_1
    //   278: isub
    //   279: getstatic eb.c : I
    //   282: iload_0
    //   283: iconst_2
    //   284: iadd
    //   285: getstatic eb.c : I
    //   288: isub
    //   289: getstatic eb.i : I
    //   292: iconst_1
    //   293: ishl
    //   294: isub
    //   295: getstatic eb.h : I
    //   298: getstatic eb.h : I
    //   301: iconst_3
    //   302: idiv
    //   303: iconst_0
    //   304: invokestatic b : (Ljavax/microedition/lcdui/Graphics;IIIIII)V
    //   307: aload #9
    //   309: getstatic eb.c : I
    //   312: iconst_2
    //   313: idiv
    //   314: getstatic eb.c : I
    //   317: getstatic eb.i : I
    //   320: getstatic eb.h : I
    //   323: getstatic eb.h : I
    //   326: iconst_3
    //   327: idiv
    //   328: iload_2
    //   329: iconst_1
    //   330: if_icmpne -> 338
    //   333: ldc 7708140
    //   335: goto -> 340
    //   338: ldc 16053492
    //   340: iload_2
    //   341: iconst_1
    //   342: if_icmpne -> 350
    //   345: ldc 4681404
    //   347: goto -> 352
    //   350: ldc 12895428
    //   352: getstatic kp.c : I
    //   355: getstatic kp.e : I
    //   358: ior
    //   359: invokestatic a : (Ljavax/microedition/lcdui/Graphics;IIIIIIII)V
    //   362: aload #9
    //   364: ldc 11842740
    //   366: invokevirtual setColor : (I)V
    //   369: aload #9
    //   371: getstatic eb.c : I
    //   374: iconst_2
    //   375: idiv
    //   376: getstatic eb.c : I
    //   379: getstatic eb.i : I
    //   382: getstatic eb.h : I
    //   385: getstatic eb.h : I
    //   388: iconst_3
    //   389: idiv
    //   390: getstatic kp.c : I
    //   393: getstatic kp.e : I
    //   396: ior
    //   397: invokestatic b : (Ljavax/microedition/lcdui/Graphics;IIIIII)V
    //   400: aload #9
    //   402: iload_0
    //   403: getstatic eb.c : I
    //   406: iconst_2
    //   407: idiv
    //   408: isub
    //   409: getstatic eb.i : I
    //   412: isub
    //   413: getstatic eb.c : I
    //   416: getstatic eb.i : I
    //   419: getstatic eb.h : I
    //   422: getstatic eb.h : I
    //   425: iconst_3
    //   426: idiv
    //   427: iload_2
    //   428: iconst_2
    //   429: if_icmpne -> 437
    //   432: ldc 7708140
    //   434: goto -> 439
    //   437: ldc 16053492
    //   439: iload_2
    //   440: iconst_2
    //   441: if_icmpne -> 449
    //   444: ldc 4681404
    //   446: goto -> 451
    //   449: ldc 12895428
    //   451: getstatic kp.d : I
    //   454: getstatic kp.f : I
    //   457: ior
    //   458: invokestatic a : (Ljavax/microedition/lcdui/Graphics;IIIIIIII)V
    //   461: aload #9
    //   463: ldc 11842740
    //   465: invokevirtual setColor : (I)V
    //   468: aload #9
    //   470: iload_0
    //   471: getstatic eb.c : I
    //   474: iconst_2
    //   475: idiv
    //   476: isub
    //   477: getstatic eb.i : I
    //   480: isub
    //   481: getstatic eb.c : I
    //   484: getstatic eb.i : I
    //   487: getstatic eb.h : I
    //   490: getstatic eb.h : I
    //   493: iconst_3
    //   494: idiv
    //   495: getstatic kp.d : I
    //   498: getstatic kp.f : I
    //   501: ior
    //   502: invokestatic b : (Ljavax/microedition/lcdui/Graphics;IIIIII)V
    //   505: new java/lang/StringBuffer
    //   508: dup
    //   509: invokespecial <init> : ()V
    //   512: ldc 'att'
    //   514: invokevirtual append : (Ljava/lang/String;)Ljava/lang/StringBuffer;
    //   517: iload_2
    //   518: iconst_1
    //   519: if_icmpne -> 527
    //   522: ldc 'sel'
    //   524: goto -> 529
    //   527: ldc ''
    //   529: invokevirtual append : (Ljava/lang/String;)Ljava/lang/StringBuffer;
    //   532: iload #4
    //   534: ifne -> 542
    //   537: ldc 'with'
    //   539: goto -> 544
    //   542: ldc ''
    //   544: invokevirtual append : (Ljava/lang/String;)Ljava/lang/StringBuffer;
    //   547: ldc '.png'
    //   549: invokevirtual append : (Ljava/lang/String;)Ljava/lang/StringBuffer;
    //   552: invokevirtual toString : ()Ljava/lang/String;
    //   555: invokestatic a : (Ljava/lang/String;)Ljavax/microedition/lcdui/Image;
    //   558: getstatic eb.h : I
    //   561: bipush #6
    //   563: isub
    //   564: invokestatic a : (Ljavax/microedition/lcdui/Image;I)Ljavax/microedition/lcdui/Image;
    //   567: astore #8
    //   569: aload #9
    //   571: aload #8
    //   573: getstatic eb.c : I
    //   576: iconst_2
    //   577: idiv
    //   578: getstatic eb.i : I
    //   581: iconst_2
    //   582: idiv
    //   583: iadd
    //   584: getstatic eb.h : I
    //   587: iconst_2
    //   588: idiv
    //   589: getstatic eb.c : I
    //   592: iadd
    //   593: iconst_3
    //   594: invokevirtual drawImage : (Ljavax/microedition/lcdui/Image;III)V
    //   597: iload #5
    //   599: ifeq -> 617
    //   602: iload_2
    //   603: iconst_2
    //   604: if_icmpne -> 612
    //   607: ldc 'editsel.png'
    //   609: goto -> 648
    //   612: ldc 'edit.png'
    //   614: goto -> 648
    //   617: iload_3
    //   618: ifeq -> 636
    //   621: iload_2
    //   622: iconst_2
    //   623: if_icmpne -> 631
    //   626: ldc 'arrowdowns.png'
    //   628: goto -> 648
    //   631: ldc 'arrowdown.png'
    //   633: goto -> 648
    //   636: iload_2
    //   637: iconst_2
    //   638: if_icmpne -> 646
    //   641: ldc 'sendsel.png'
    //   643: goto -> 648
    //   646: ldc 'send.png'
    //   648: invokestatic a : (Ljava/lang/String;)Ljavax/microedition/lcdui/Image;
    //   651: getstatic eb.h : I
    //   654: bipush #6
    //   656: isub
    //   657: invokestatic a : (Ljavax/microedition/lcdui/Image;I)Ljavax/microedition/lcdui/Image;
    //   660: astore #8
    //   662: aload #9
    //   664: aload #8
    //   666: iload_0
    //   667: getstatic eb.c : I
    //   670: iconst_2
    //   671: idiv
    //   672: isub
    //   673: getstatic eb.i : I
    //   676: iconst_2
    //   677: idiv
    //   678: isub
    //   679: getstatic eb.h : I
    //   682: iconst_2
    //   683: idiv
    //   684: getstatic eb.c : I
    //   687: iadd
    //   688: iconst_3
    //   689: invokevirtual drawImage : (Ljavax/microedition/lcdui/Image;III)V
    //   692: getstatic kp.a : Ljava/util/Hashtable;
    //   695: aload #6
    //   697: aload #7
    //   699: invokevirtual put : (Ljava/lang/Object;Ljava/lang/Object;)Ljava/lang/Object;
    //   702: pop
    //   703: aload #7
    //   705: areturn
  }
  
  static Image b(int paramInt1, int paramInt2) {
    // Byte code:
    //   0: getstatic gz.a : Lgz;
    //   3: getfield b : Ljavax/microedition/lcdui/Font;
    //   6: invokevirtual getHeight : ()I
    //   9: istore_2
    //   10: new java/lang/StringBuffer
    //   13: dup
    //   14: invokespecial <init> : ()V
    //   17: ldc 'pm'
    //   19: invokevirtual append : (Ljava/lang/String;)Ljava/lang/StringBuffer;
    //   22: iload_0
    //   23: invokevirtual append : (I)Ljava/lang/StringBuffer;
    //   26: ldc 'x'
    //   28: invokevirtual append : (Ljava/lang/String;)Ljava/lang/StringBuffer;
    //   31: iload_1
    //   32: invokevirtual append : (I)Ljava/lang/StringBuffer;
    //   35: invokevirtual toString : ()Ljava/lang/String;
    //   38: astore_3
    //   39: getstatic kp.a : Ljava/util/Hashtable;
    //   42: aload_3
    //   43: invokevirtual get : (Ljava/lang/Object;)Ljava/lang/Object;
    //   46: checkcast javax/microedition/lcdui/Image
    //   49: dup
    //   50: astore #4
    //   52: ifnull -> 58
    //   55: aload #4
    //   57: areturn
    //   58: iload_1
    //   59: iload_0
    //   60: invokestatic createImage : (II)Ljavax/microedition/lcdui/Image;
    //   63: dup
    //   64: astore #4
    //   66: invokevirtual getGraphics : ()Ljavax/microedition/lcdui/Graphics;
    //   69: iconst_0
    //   70: iconst_0
    //   71: iload_1
    //   72: iload_0
    //   73: ldc 4539465
    //   75: ldc 2236710
    //   77: invokestatic c : (Ljavax/microedition/lcdui/Graphics;IIIIII)V
    //   80: iload_2
    //   81: iconst_2
    //   82: idiv
    //   83: aload #4
    //   85: invokestatic a : (ILjavax/microedition/lcdui/Image;)Ljavax/microedition/lcdui/Image;
    //   88: astore #4
    //   90: getstatic kp.a : Ljava/util/Hashtable;
    //   93: aload_3
    //   94: aload #4
    //   96: invokevirtual put : (Ljava/lang/Object;Ljava/lang/Object;)Ljava/lang/Object;
    //   99: pop
    //   100: aload #4
    //   102: areturn
  }
  
  static Image a(int paramInt) {
    // Byte code:
    //   0: new java/lang/StringBuffer
    //   3: dup
    //   4: invokespecial <init> : ()V
    //   7: ldc 'cdivider'
    //   9: invokevirtual append : (Ljava/lang/String;)Ljava/lang/StringBuffer;
    //   12: iload_0
    //   13: invokevirtual append : (I)Ljava/lang/StringBuffer;
    //   16: invokevirtual toString : ()Ljava/lang/String;
    //   19: astore_1
    //   20: getstatic kp.a : Ljava/util/Hashtable;
    //   23: aload_1
    //   24: invokevirtual get : (Ljava/lang/Object;)Ljava/lang/Object;
    //   27: checkcast javax/microedition/lcdui/Image
    //   30: dup
    //   31: astore_2
    //   32: ifnull -> 37
    //   35: aload_2
    //   36: areturn
    //   37: getstatic gz.a : Lgz;
    //   40: getfield a : Ljavax/microedition/lcdui/Font;
    //   43: invokevirtual getHeight : ()I
    //   46: getstatic gz.a : Lgz;
    //   49: getfield a : Lcp;
    //   52: invokevirtual a : ()I
    //   55: iadd
    //   56: istore_2
    //   57: iload_0
    //   58: iload_2
    //   59: invokestatic createImage : (II)Ljavax/microedition/lcdui/Image;
    //   62: dup
    //   63: astore_2
    //   64: invokevirtual getGraphics : ()Ljavax/microedition/lcdui/Graphics;
    //   67: dup
    //   68: astore_3
    //   69: ldc 16777215
    //   71: invokevirtual setColor : (I)V
    //   74: aload_3
    //   75: iconst_0
    //   76: iconst_0
    //   77: iload_0
    //   78: getstatic gz.a : Lgz;
    //   81: getfield a : Ljavax/microedition/lcdui/Font;
    //   84: invokevirtual getHeight : ()I
    //   87: getstatic gz.a : Lgz;
    //   90: getfield a : Lcp;
    //   93: invokevirtual a : ()I
    //   96: iadd
    //   97: invokevirtual fillRect : (IIII)V
    //   100: getstatic kp.a : Ljava/util/Hashtable;
    //   103: aload_1
    //   104: aload_2
    //   105: invokevirtual put : (Ljava/lang/Object;Ljava/lang/Object;)Ljava/lang/Object;
    //   108: pop
    //   109: aload_2
    //   110: areturn
  }
  
  public static Image a(int paramInt1, int paramInt2, boolean paramBoolean1, boolean paramBoolean2) {
    // Byte code:
    //   0: new java/lang/StringBuffer
    //   3: dup
    //   4: invokespecial <init> : ()V
    //   7: ldc 'mh'
    //   9: invokevirtual append : (Ljava/lang/String;)Ljava/lang/StringBuffer;
    //   12: iload_0
    //   13: invokevirtual append : (I)Ljava/lang/StringBuffer;
    //   16: ldc 'x'
    //   18: invokevirtual append : (Ljava/lang/String;)Ljava/lang/StringBuffer;
    //   21: iload_1
    //   22: invokevirtual append : (I)Ljava/lang/StringBuffer;
    //   25: ldc 'x'
    //   27: invokevirtual append : (Ljava/lang/String;)Ljava/lang/StringBuffer;
    //   30: iload_2
    //   31: ifeq -> 38
    //   34: iconst_1
    //   35: goto -> 39
    //   38: iconst_0
    //   39: invokevirtual append : (I)Ljava/lang/StringBuffer;
    //   42: iload_3
    //   43: ifeq -> 50
    //   46: iconst_1
    //   47: goto -> 51
    //   50: iconst_0
    //   51: invokevirtual append : (I)Ljava/lang/StringBuffer;
    //   54: invokevirtual toString : ()Ljava/lang/String;
    //   57: astore #4
    //   59: getstatic kp.a : Ljava/util/Hashtable;
    //   62: aload #4
    //   64: invokevirtual get : (Ljava/lang/Object;)Ljava/lang/Object;
    //   67: checkcast javax/microedition/lcdui/Image
    //   70: dup
    //   71: astore #5
    //   73: ifnull -> 79
    //   76: aload #5
    //   78: areturn
    //   79: iload_0
    //   80: iload_1
    //   81: invokestatic createImage : (II)Ljavax/microedition/lcdui/Image;
    //   84: dup
    //   85: astore #5
    //   87: invokevirtual getGraphics : ()Ljavax/microedition/lcdui/Graphics;
    //   90: dup
    //   91: astore #6
    //   93: iload_3
    //   94: ifeq -> 102
    //   97: ldc 13294072
    //   99: goto -> 104
    //   102: ldc 15000804
    //   104: invokevirtual setColor : (I)V
    //   107: aload #6
    //   109: iconst_0
    //   110: iconst_0
    //   111: iload_0
    //   112: iload_1
    //   113: getstatic cc.a : I
    //   116: iload_3
    //   117: ifeq -> 126
    //   120: getstatic kp.c : I
    //   123: goto -> 129
    //   126: getstatic kp.d : I
    //   129: invokestatic a : (Ljavax/microedition/lcdui/Graphics;IIIIII)V
    //   132: iload_2
    //   133: ifne -> 145
    //   136: getstatic v.a : Lv;
    //   139: getfield a : Z
    //   142: ifeq -> 197
    //   145: aload #6
    //   147: iload_2
    //   148: ifeq -> 156
    //   151: ldc 4681404
    //   153: goto -> 167
    //   156: iload_3
    //   157: ifeq -> 165
    //   160: ldc 9084874
    //   162: goto -> 167
    //   165: ldc 11842740
    //   167: invokevirtual setColor : (I)V
    //   170: aload #6
    //   172: iconst_0
    //   173: iconst_0
    //   174: iload_0
    //   175: iload_1
    //   176: iconst_1
    //   177: iadd
    //   178: getstatic cc.a : I
    //   181: iload_3
    //   182: ifeq -> 191
    //   185: getstatic kp.c : I
    //   188: goto -> 194
    //   191: getstatic kp.d : I
    //   194: invokestatic b : (Ljavax/microedition/lcdui/Graphics;IIIIII)V
    //   197: getstatic kp.a : Ljava/util/Hashtable;
    //   200: aload #4
    //   202: aload #5
    //   204: invokevirtual put : (Ljava/lang/Object;Ljava/lang/Object;)Ljava/lang/Object;
    //   207: pop
    //   208: aload #5
    //   210: areturn
  }
  
  public static Image a(int paramInt, boolean paramBoolean1, boolean paramBoolean2) {
    // Byte code:
    //   0: new java/lang/StringBuffer
    //   3: dup
    //   4: invokespecial <init> : ()V
    //   7: ldc 'mf'
    //   9: invokevirtual append : (Ljava/lang/String;)Ljava/lang/StringBuffer;
    //   12: iload_0
    //   13: invokevirtual append : (I)Ljava/lang/StringBuffer;
    //   16: ldc 'x'
    //   18: invokevirtual append : (Ljava/lang/String;)Ljava/lang/StringBuffer;
    //   21: iload_1
    //   22: ifeq -> 29
    //   25: iconst_1
    //   26: goto -> 30
    //   29: iconst_0
    //   30: invokevirtual append : (I)Ljava/lang/StringBuffer;
    //   33: iload_2
    //   34: ifeq -> 41
    //   37: iconst_1
    //   38: goto -> 42
    //   41: iconst_0
    //   42: invokevirtual append : (I)Ljava/lang/StringBuffer;
    //   45: invokevirtual toString : ()Ljava/lang/String;
    //   48: astore_3
    //   49: getstatic kp.a : Ljava/util/Hashtable;
    //   52: aload_3
    //   53: invokevirtual get : (Ljava/lang/Object;)Ljava/lang/Object;
    //   56: checkcast javax/microedition/lcdui/Image
    //   59: dup
    //   60: astore #4
    //   62: ifnull -> 68
    //   65: aload #4
    //   67: areturn
    //   68: iload_0
    //   69: getstatic cc.a : I
    //   72: invokestatic createImage : (II)Ljavax/microedition/lcdui/Image;
    //   75: dup
    //   76: astore #4
    //   78: invokevirtual getGraphics : ()Ljavax/microedition/lcdui/Graphics;
    //   81: dup
    //   82: astore #5
    //   84: iload_2
    //   85: ifeq -> 93
    //   88: ldc 13294072
    //   90: goto -> 95
    //   93: ldc 15000804
    //   95: invokevirtual setColor : (I)V
    //   98: aload #5
    //   100: iconst_0
    //   101: iconst_0
    //   102: iload_0
    //   103: getstatic cc.a : I
    //   106: getstatic cc.a : I
    //   109: getstatic kp.e : I
    //   112: getstatic kp.f : I
    //   115: ior
    //   116: invokestatic a : (Ljavax/microedition/lcdui/Graphics;IIIIII)V
    //   119: iload_1
    //   120: ifne -> 132
    //   123: getstatic v.a : Lv;
    //   126: getfield a : Z
    //   129: ifeq -> 180
    //   132: aload #5
    //   134: iload_1
    //   135: ifeq -> 143
    //   138: ldc 4681404
    //   140: goto -> 154
    //   143: iload_2
    //   144: ifeq -> 152
    //   147: ldc 9084874
    //   149: goto -> 154
    //   152: ldc 11842740
    //   154: invokevirtual setColor : (I)V
    //   157: aload #5
    //   159: iconst_0
    //   160: iconst_m1
    //   161: iload_0
    //   162: getstatic cc.a : I
    //   165: iconst_1
    //   166: iadd
    //   167: getstatic cc.a : I
    //   170: getstatic kp.e : I
    //   173: getstatic kp.f : I
    //   176: ior
    //   177: invokestatic b : (Ljavax/microedition/lcdui/Graphics;IIIIII)V
    //   180: getstatic kp.a : Ljava/util/Hashtable;
    //   183: aload_3
    //   184: aload #4
    //   186: invokevirtual put : (Ljava/lang/Object;Ljava/lang/Object;)Ljava/lang/Object;
    //   189: pop
    //   190: aload #4
    //   192: areturn
  }
  
  public static Image b(int paramInt1, int paramInt2, boolean paramBoolean1, boolean paramBoolean2) {
    // Byte code:
    //   0: new java/lang/StringBuffer
    //   3: dup
    //   4: invokespecial <init> : ()V
    //   7: ldc 'mp'
    //   9: invokevirtual append : (Ljava/lang/String;)Ljava/lang/StringBuffer;
    //   12: iload_0
    //   13: invokevirtual append : (I)Ljava/lang/StringBuffer;
    //   16: ldc 'x'
    //   18: invokevirtual append : (Ljava/lang/String;)Ljava/lang/StringBuffer;
    //   21: iload_1
    //   22: invokevirtual append : (I)Ljava/lang/StringBuffer;
    //   25: ldc 'x'
    //   27: invokevirtual append : (Ljava/lang/String;)Ljava/lang/StringBuffer;
    //   30: iload_2
    //   31: ifeq -> 38
    //   34: iconst_1
    //   35: goto -> 39
    //   38: iconst_0
    //   39: invokevirtual append : (I)Ljava/lang/StringBuffer;
    //   42: iload_3
    //   43: ifeq -> 50
    //   46: iconst_1
    //   47: goto -> 51
    //   50: iconst_0
    //   51: invokevirtual append : (I)Ljava/lang/StringBuffer;
    //   54: invokevirtual toString : ()Ljava/lang/String;
    //   57: astore #4
    //   59: getstatic kp.a : Ljava/util/Hashtable;
    //   62: aload #4
    //   64: invokevirtual get : (Ljava/lang/Object;)Ljava/lang/Object;
    //   67: checkcast javax/microedition/lcdui/Image
    //   70: dup
    //   71: astore #5
    //   73: ifnull -> 79
    //   76: aload #5
    //   78: areturn
    //   79: iload_0
    //   80: iload_1
    //   81: invokestatic createImage : (II)Ljavax/microedition/lcdui/Image;
    //   84: dup
    //   85: astore #5
    //   87: invokevirtual getGraphics : ()Ljavax/microedition/lcdui/Graphics;
    //   90: dup
    //   91: astore #6
    //   93: iload_3
    //   94: ifeq -> 102
    //   97: ldc 13294072
    //   99: goto -> 104
    //   102: ldc 15000804
    //   104: invokevirtual setColor : (I)V
    //   107: aload #6
    //   109: iconst_0
    //   110: iconst_0
    //   111: iload_0
    //   112: iload_1
    //   113: invokevirtual fillRect : (IIII)V
    //   116: iload_2
    //   117: ifne -> 129
    //   120: getstatic v.a : Lv;
    //   123: getfield a : Z
    //   126: ifeq -> 167
    //   129: aload #6
    //   131: iload_2
    //   132: ifeq -> 140
    //   135: ldc 4681404
    //   137: goto -> 151
    //   140: iload_3
    //   141: ifeq -> 149
    //   144: ldc 9084874
    //   146: goto -> 151
    //   149: ldc 11842740
    //   151: invokevirtual setColor : (I)V
    //   154: aload #6
    //   156: iconst_0
    //   157: iconst_m1
    //   158: iload_0
    //   159: iconst_1
    //   160: isub
    //   161: iload_1
    //   162: iconst_2
    //   163: iadd
    //   164: invokevirtual drawRect : (IIII)V
    //   167: getstatic kp.a : Ljava/util/Hashtable;
    //   170: aload #4
    //   172: aload #5
    //   174: invokevirtual put : (Ljava/lang/Object;Ljava/lang/Object;)Ljava/lang/Object;
    //   177: pop
    //   178: aload #5
    //   180: areturn
  }
}


/* Location:              /home/kost//latest.jar!/kp.class
 * Java compiler version: 4 (48.0)
 * JD-Core Version:       1.1.3
 */