import java.util.TimerTask;

final class kx extends TimerTask {
  private final gz a;
  
  kx(gz paramgz) {
    this.a = paramgz;
  }
  
  public final void run() {
    // Byte code:
    //   0: aload_0
    //   1: getfield a : Lgz;
    //   4: getfield a : B
    //   7: iconst_m1
    //   8: if_icmpeq -> 92
    //   11: aload_0
    //   12: getfield a : Lgz;
    //   15: getfield a : B
    //   18: ifne -> 78
    //   21: getstatic v.a : Lv;
    //   24: getfield e : Z
    //   27: ifeq -> 58
    //   30: aload_0
    //   31: getfield a : Lgz;
    //   34: getfield b : Lkz;
    //   37: getfield b : [I
    //   40: iconst_0
    //   41: iconst_0
    //   42: iastore
    //   43: aload_0
    //   44: getfield a : Lgz;
    //   47: getfield b : Lkz;
    //   50: bipush #100
    //   52: invokevirtual a : (I)V
    //   55: goto -> 71
    //   58: aload_0
    //   59: getfield a : Lgz;
    //   62: getfield b : Lkz;
    //   65: getfield c : [I
    //   68: iconst_0
    //   69: iconst_0
    //   70: iastore
    //   71: aload_0
    //   72: getfield a : Lgz;
    //   75: invokevirtual b : ()V
    //   78: aload_0
    //   79: getfield a : Lgz;
    //   82: dup
    //   83: getfield a : B
    //   86: iconst_1
    //   87: isub
    //   88: i2b
    //   89: putfield a : B
    //   92: aload_0
    //   93: getfield a : Lgz;
    //   96: getfield a : J
    //   99: invokestatic currentTimeMillis : ()J
    //   102: ldc2_w 60000
    //   105: ldiv
    //   106: lcmp
    //   107: ifeq -> 148
    //   110: aload_0
    //   111: getfield a : Lgz;
    //   114: invokestatic currentTimeMillis : ()J
    //   117: ldc2_w 60000
    //   120: ldiv
    //   121: putfield a : J
    //   124: aload_0
    //   125: getfield a : Lgz;
    //   128: invokestatic currentTimeMillis : ()J
    //   131: ldc2_w 1000
    //   134: ldiv
    //   135: invokestatic b : (J)Ljava/lang/String;
    //   138: putfield a : Ljava/lang/String;
    //   141: aload_0
    //   142: getfield a : Lgz;
    //   145: invokevirtual b : ()V
    //   148: aload_0
    //   149: getfield a : Lgz;
    //   152: getfield a : Lla;
    //   155: ifnull -> 184
    //   158: aload_0
    //   159: getfield a : Lgz;
    //   162: getfield a : Lla;
    //   165: instanceof hs
    //   168: ifeq -> 184
    //   171: aload_0
    //   172: getfield a : Lgz;
    //   175: getfield a : Lla;
    //   178: checkcast hs
    //   181: invokevirtual g : ()V
    //   184: aload_0
    //   185: getfield a : Lgz;
    //   188: getfield a : Lla;
    //   191: ifnull -> 271
    //   194: aload_0
    //   195: getfield a : Lgz;
    //   198: getfield a : Lla;
    //   201: instanceof ea
    //   204: ifeq -> 271
    //   207: aload_0
    //   208: getfield a : Lgz;
    //   211: getfield a : Lla;
    //   214: checkcast ea
    //   217: getfield a : Ljp;
    //   220: invokevirtual c : ()Z
    //   223: ifne -> 258
    //   226: aload_0
    //   227: getfield a : Lgz;
    //   230: getfield a : Lla;
    //   233: checkcast ea
    //   236: getfield c : Z
    //   239: ifne -> 258
    //   242: aload_0
    //   243: getfield a : Lgz;
    //   246: getfield a : Lla;
    //   249: checkcast ea
    //   252: getfield a : I
    //   255: ifle -> 271
    //   258: aload_0
    //   259: getfield a : Lgz;
    //   262: getfield a : Lla;
    //   265: checkcast ea
    //   268: invokevirtual c : ()V
    //   271: return
  }
}


/* Location:              /home/kost/Загрузки/latest.jar!/kx.class
 * Java compiler version: 4 (48.0)
 * JD-Core Version:       1.1.3
 */