import java.util.Vector;
import javax.microedition.lcdui.Graphics;
import javax.microedition.lcdui.Image;

public class la {
  public Vector b;
  
  public int e;
  
  public int f;
  
  public int g;
  
  public int h;
  
  private int a;
  
  public static int i = ((gz)gz.a).a.getHeight() / 2;
  
  private int b;
  
  private boolean a;
  
  private boolean b = new Vector();
  
  public boolean d;
  
  public String c;
  
  public String d;
  
  boolean e;
  
  private int c;
  
  private int d;
  
  int j;
  
  ba a;
  
  public void a(ay paramay) {}
  
  public la(String paramString) {
    c(paramString);
  }
  
  public la a() {
    // Byte code:
    //   0: aload_0
    //   1: getfield b : Ljava/util/Vector;
    //   4: invokevirtual removeAllElements : ()V
    //   7: invokestatic gc : ()V
    //   10: getstatic gz.a : Lgz;
    //   13: ldc 'general.outOfMemory'
    //   15: invokestatic a : (Ljava/lang/String;)Ljava/lang/String;
    //   18: invokevirtual a : (Ljava/lang/String;)V
    //   21: getstatic gz.a : Lgz;
    //   24: iconst_0
    //   25: invokevirtual b : (Z)V
    //   28: aload_0
    //   29: areturn
  }
  
  public la() {}
  
  public final void f(int paramInt1, int paramInt2) {
    a(paramInt1, -1, paramInt2);
  }
  
  public final void g(int paramInt1, int paramInt2) {
    a(paramInt1, paramInt2, -1);
  }
  
  public int b() {
    return gz.a.getWidth();
  }
  
  private void a(int paramInt1, int paramInt2, int paramInt3) {
    // Byte code:
    //   0: getstatic la.i : I
    //   3: istore #4
    //   5: aload_0
    //   6: getfield b : Z
    //   9: ifeq -> 16
    //   12: iconst_0
    //   13: goto -> 19
    //   16: getstatic la.i : I
    //   19: istore #5
    //   21: iload_1
    //   22: getstatic la.i : I
    //   25: iconst_1
    //   26: ishl
    //   27: isub
    //   28: istore #6
    //   30: aload_0
    //   31: instanceof ba
    //   34: istore #7
    //   36: iconst_0
    //   37: istore #8
    //   39: iload #8
    //   41: aload_0
    //   42: getfield b : Ljava/util/Vector;
    //   45: invokevirtual size : ()I
    //   48: if_icmpge -> 224
    //   51: aload_0
    //   52: getfield b : Ljava/util/Vector;
    //   55: iload #8
    //   57: invokevirtual elementAt : (I)Ljava/lang/Object;
    //   60: checkcast ay
    //   63: dup
    //   64: astore #9
    //   66: ifnull -> 218
    //   69: aload #9
    //   71: iload #7
    //   73: putfield l : Z
    //   76: aload #9
    //   78: getfield q : Z
    //   81: ifeq -> 99
    //   84: aload #9
    //   86: aload #9
    //   88: iconst_0
    //   89: dup_x1
    //   90: putfield g : I
    //   93: putfield f : I
    //   96: goto -> 218
    //   99: aload #9
    //   101: instanceof fp
    //   104: ifeq -> 119
    //   107: aload #9
    //   109: iload_1
    //   110: putfield d : I
    //   113: iconst_0
    //   114: istore #4
    //   116: goto -> 133
    //   119: aload #9
    //   121: iload #6
    //   123: putfield d : I
    //   126: aload #9
    //   128: iload #4
    //   130: putfield f : I
    //   133: aload #9
    //   135: getfield p : Z
    //   138: ifeq -> 144
    //   141: iinc #5, 1
    //   144: aload #9
    //   146: iload #5
    //   148: putfield g : I
    //   151: iload #8
    //   153: aload_0
    //   154: getfield b : Ljava/util/Vector;
    //   157: invokevirtual size : ()I
    //   160: iload_3
    //   161: isub
    //   162: iconst_1
    //   163: isub
    //   164: if_icmpgt -> 173
    //   167: iload #8
    //   169: iload_2
    //   170: if_icmpge -> 178
    //   173: aload #9
    //   175: invokevirtual d : ()V
    //   178: iload #5
    //   180: aload #9
    //   182: getfield n : Z
    //   185: ifeq -> 192
    //   188: iconst_0
    //   189: goto -> 195
    //   192: getstatic la.i : I
    //   195: aload #9
    //   197: getfield e : I
    //   200: iadd
    //   201: aload #9
    //   203: getfield o : Z
    //   206: ifeq -> 213
    //   209: iconst_1
    //   210: goto -> 214
    //   213: iconst_0
    //   214: iadd
    //   215: iadd
    //   216: istore #5
    //   218: iinc #8, 1
    //   221: goto -> 39
    //   224: aload_0
    //   225: iload #5
    //   227: putfield e : I
    //   230: return
  }
  
  public void a(Graphics paramGraphics, int paramInt) {
    a(paramGraphics, paramInt, ((gz)gz.a).g, gz.a.getWidth(), gz.a.c(), gz.a.getHeight());
  }
  
  public final void a(Graphics paramGraphics, int paramInt1, int paramInt2) {
    a(paramGraphics, paramInt2, ((gz)gz.a).g, gz.a.getWidth(), paramInt1, gz.a.getHeight());
  }
  
  public void a(Graphics paramGraphics, int paramInt1, int paramInt2, int paramInt3, int paramInt4, int paramInt5) {
    // Byte code:
    //   0: aload_0
    //   1: iload #5
    //   3: putfield j : I
    //   6: getstatic gz.a : Lgz;
    //   9: aload_0
    //   10: getfield j : I
    //   13: putfield h : I
    //   16: aload_1
    //   17: invokevirtual getClipX : ()I
    //   20: istore #7
    //   22: aload_1
    //   23: invokevirtual getClipY : ()I
    //   26: istore #8
    //   28: aload_1
    //   29: invokevirtual getClipWidth : ()I
    //   32: istore #9
    //   34: aload_1
    //   35: invokevirtual getClipHeight : ()I
    //   38: istore #10
    //   40: aload_1
    //   41: iload_2
    //   42: iload_3
    //   43: iload #4
    //   45: iload #5
    //   47: invokevirtual setClip : (IIII)V
    //   50: iconst_0
    //   51: istore #11
    //   53: aload_0
    //   54: getfield a : I
    //   57: ifeq -> 143
    //   60: getstatic gz.a : Lgz;
    //   63: getfield b : Z
    //   66: ifne -> 143
    //   69: aload_0
    //   70: aload_0
    //   71: getfield a : I
    //   74: bipush #92
    //   76: imul
    //   77: bipush #100
    //   79: idiv
    //   80: putfield a : I
    //   83: aload_0
    //   84: getfield a : I
    //   87: sipush #255
    //   90: if_icmpgt -> 103
    //   93: aload_0
    //   94: getfield a : I
    //   97: sipush #-255
    //   100: if_icmpge -> 135
    //   103: aload_0
    //   104: dup
    //   105: getfield g : I
    //   108: aload_0
    //   109: getfield a : I
    //   112: sipush #256
    //   115: idiv
    //   116: iadd
    //   117: putfield g : I
    //   120: aload_0
    //   121: invokespecial e : ()V
    //   124: aload_0
    //   125: aload_0
    //   126: getfield g : I
    //   129: putfield f : I
    //   132: goto -> 140
    //   135: aload_0
    //   136: iconst_0
    //   137: putfield a : I
    //   140: iconst_1
    //   141: istore #11
    //   143: aload_0
    //   144: invokespecial e : ()V
    //   147: aload_0
    //   148: getfield g : I
    //   151: aload_0
    //   152: getfield f : I
    //   155: if_icmpeq -> 256
    //   158: getstatic v.a : Lv;
    //   161: getfield f : Z
    //   164: ifne -> 178
    //   167: aload_0
    //   168: aload_0
    //   169: getfield g : I
    //   172: putfield f : I
    //   175: goto -> 242
    //   178: aload_0
    //   179: getfield g : I
    //   182: aload_0
    //   183: getfield f : I
    //   186: isub
    //   187: invokestatic abs : (I)I
    //   190: iconst_4
    //   191: if_icmpge -> 222
    //   194: aload_0
    //   195: dup
    //   196: getfield f : I
    //   199: aload_0
    //   200: getfield g : I
    //   203: aload_0
    //   204: getfield f : I
    //   207: if_icmple -> 214
    //   210: iconst_1
    //   211: goto -> 215
    //   214: iconst_m1
    //   215: iadd
    //   216: putfield f : I
    //   219: goto -> 242
    //   222: aload_0
    //   223: dup
    //   224: getfield f : I
    //   227: aload_0
    //   228: getfield g : I
    //   231: aload_0
    //   232: getfield f : I
    //   235: isub
    //   236: iconst_4
    //   237: idiv
    //   238: iadd
    //   239: putfield f : I
    //   242: aload_0
    //   243: getfield g : I
    //   246: aload_0
    //   247: getfield f : I
    //   250: if_icmpeq -> 256
    //   253: iconst_1
    //   254: istore #11
    //   256: aload_0
    //   257: invokespecial h : ()V
    //   260: aload_0
    //   261: getfield b : Z
    //   264: ifeq -> 271
    //   267: iconst_0
    //   268: goto -> 274
    //   271: getstatic la.i : I
    //   274: istore #12
    //   276: iload_3
    //   277: aload_0
    //   278: getfield f : I
    //   281: isub
    //   282: istore_3
    //   283: iload #4
    //   285: getstatic la.i : I
    //   288: iconst_1
    //   289: ishl
    //   290: isub
    //   291: istore #13
    //   293: aload_0
    //   294: instanceof ba
    //   297: istore #14
    //   299: iconst_0
    //   300: istore #15
    //   302: iload #15
    //   304: aload_0
    //   305: getfield b : Ljava/util/Vector;
    //   308: invokevirtual size : ()I
    //   311: if_icmpge -> 630
    //   314: aload_0
    //   315: getfield b : Ljava/util/Vector;
    //   318: iload #15
    //   320: invokevirtual elementAt : (I)Ljava/lang/Object;
    //   323: checkcast ay
    //   326: dup
    //   327: astore #16
    //   329: ifnull -> 624
    //   332: aload #16
    //   334: iload #14
    //   336: putfield l : Z
    //   339: getstatic gz.a : Lgz;
    //   342: getfield c : Z
    //   345: ifeq -> 367
    //   348: aload #16
    //   350: iload #15
    //   352: aload_0
    //   353: getfield h : I
    //   356: if_icmpne -> 363
    //   359: iconst_1
    //   360: goto -> 364
    //   363: iconst_0
    //   364: putfield k : Z
    //   367: aload #16
    //   369: getfield q : Z
    //   372: ifeq -> 390
    //   375: aload #16
    //   377: aload #16
    //   379: iconst_0
    //   380: dup_x1
    //   381: putfield g : I
    //   384: putfield f : I
    //   387: goto -> 624
    //   390: aload #16
    //   392: instanceof fp
    //   395: ifeq -> 414
    //   398: aload #16
    //   400: iload #4
    //   402: putfield d : I
    //   405: aload #16
    //   407: iconst_0
    //   408: putfield f : I
    //   411: goto -> 429
    //   414: aload #16
    //   416: iload #13
    //   418: putfield d : I
    //   421: aload #16
    //   423: getstatic la.i : I
    //   426: putfield f : I
    //   429: aload #16
    //   431: getfield p : Z
    //   434: ifeq -> 463
    //   437: aload_1
    //   438: ldc 14606302
    //   440: invokevirtual setColor : (I)V
    //   443: aload_1
    //   444: iload_2
    //   445: iload #12
    //   447: iload_3
    //   448: iadd
    //   449: iload #4
    //   451: iload_2
    //   452: iadd
    //   453: iload #12
    //   455: iload_3
    //   456: iadd
    //   457: invokevirtual drawLine : (IIII)V
    //   460: iinc #12, 1
    //   463: aload #16
    //   465: iload #12
    //   467: putfield g : I
    //   470: aload #16
    //   472: getfield g : I
    //   475: aload #16
    //   477: getfield e : I
    //   480: iadd
    //   481: aload_0
    //   482: getfield f : I
    //   485: isub
    //   486: ifle -> 584
    //   489: aload #16
    //   491: getfield g : I
    //   494: aload_0
    //   495: getfield f : I
    //   498: isub
    //   499: iload #5
    //   501: if_icmpge -> 564
    //   504: aload_0
    //   505: aload #16
    //   507: invokevirtual a : (Lay;)V
    //   510: aload #16
    //   512: aload_1
    //   513: iload_3
    //   514: iload_2
    //   515: invokevirtual a : (Ljavax/microedition/lcdui/Graphics;II)V
    //   518: aload #16
    //   520: getfield o : Z
    //   523: ifeq -> 584
    //   526: aload_1
    //   527: ldc 14606302
    //   529: invokevirtual setColor : (I)V
    //   532: aload_1
    //   533: iload_2
    //   534: iload #12
    //   536: iload_3
    //   537: iadd
    //   538: aload #16
    //   540: getfield e : I
    //   543: iadd
    //   544: iload #4
    //   546: iload_2
    //   547: iadd
    //   548: iload #12
    //   550: iload_3
    //   551: iadd
    //   552: aload #16
    //   554: getfield e : I
    //   557: iadd
    //   558: invokevirtual drawLine : (IIII)V
    //   561: goto -> 584
    //   564: aload #16
    //   566: getfield g : I
    //   569: aload_0
    //   570: getfield f : I
    //   573: isub
    //   574: iload #6
    //   576: if_icmpge -> 584
    //   579: aload #16
    //   581: invokevirtual d : ()V
    //   584: iload #12
    //   586: aload #16
    //   588: getfield n : Z
    //   591: ifeq -> 598
    //   594: iconst_0
    //   595: goto -> 601
    //   598: getstatic la.i : I
    //   601: aload #16
    //   603: getfield e : I
    //   606: iadd
    //   607: aload #16
    //   609: getfield o : Z
    //   612: ifeq -> 619
    //   615: iconst_1
    //   616: goto -> 620
    //   619: iconst_0
    //   620: iadd
    //   621: iadd
    //   622: istore #12
    //   624: iinc #15, 1
    //   627: goto -> 302
    //   630: aload_0
    //   631: aload_0
    //   632: getfield d : I
    //   635: iload #5
    //   637: if_icmpne -> 687
    //   640: aload_0
    //   641: getfield c : I
    //   644: iload #4
    //   646: if_icmpne -> 687
    //   649: aload_0
    //   650: getfield e : I
    //   653: iload #12
    //   655: if_icmpge -> 669
    //   658: aload_0
    //   659: getfield e : I
    //   662: aload_0
    //   663: getfield j : I
    //   666: if_icmple -> 687
    //   669: aload_0
    //   670: getfield e : I
    //   673: iload #12
    //   675: if_icmple -> 691
    //   678: iload #12
    //   680: aload_0
    //   681: getfield j : I
    //   684: if_icmpgt -> 691
    //   687: iconst_1
    //   688: goto -> 692
    //   691: iconst_0
    //   692: putfield a : Z
    //   695: aload_0
    //   696: iload #4
    //   698: putfield c : I
    //   701: aload_0
    //   702: iload #5
    //   704: putfield d : I
    //   707: aload_0
    //   708: iload #12
    //   710: putfield e : I
    //   713: aload_0
    //   714: getfield e : I
    //   717: aload_0
    //   718: getfield j : I
    //   721: if_icmple -> 756
    //   724: aload_0
    //   725: getfield g : I
    //   728: aload_0
    //   729: getfield j : I
    //   732: iadd
    //   733: aload_0
    //   734: getfield e : I
    //   737: if_icmple -> 756
    //   740: aload_0
    //   741: aload_0
    //   742: getfield e : I
    //   745: aload_0
    //   746: getfield j : I
    //   749: isub
    //   750: putfield g : I
    //   753: goto -> 768
    //   756: aload_0
    //   757: getfield g : I
    //   760: ifge -> 768
    //   763: aload_0
    //   764: iconst_0
    //   765: putfield g : I
    //   768: aload_0
    //   769: getfield g : I
    //   772: aload_0
    //   773: getfield f : I
    //   776: if_icmpeq -> 782
    //   779: iconst_1
    //   780: istore #11
    //   782: aload_1
    //   783: iload #7
    //   785: iload #8
    //   787: iload #9
    //   789: iload #10
    //   791: invokevirtual setClip : (IIII)V
    //   794: aload_0
    //   795: getfield a : Z
    //   798: ifeq -> 859
    //   801: iconst_0
    //   802: istore #15
    //   804: iload #15
    //   806: aload_0
    //   807: getfield b : Ljava/util/Vector;
    //   810: invokevirtual size : ()I
    //   813: if_icmpge -> 852
    //   816: aload_0
    //   817: getfield b : Ljava/util/Vector;
    //   820: iload #15
    //   822: invokevirtual elementAt : (I)Ljava/lang/Object;
    //   825: instanceof r
    //   828: ifeq -> 846
    //   831: aload_0
    //   832: getfield b : Ljava/util/Vector;
    //   835: iload #15
    //   837: invokevirtual elementAt : (I)Ljava/lang/Object;
    //   840: checkcast r
    //   843: invokevirtual f : ()V
    //   846: iinc #15, 1
    //   849: goto -> 804
    //   852: getstatic gz.a : Lgz;
    //   855: invokevirtual b : ()V
    //   858: return
    //   859: aload_0
    //   860: getfield a : Z
    //   863: ifne -> 877
    //   866: iload #11
    //   868: ifeq -> 877
    //   871: getstatic gz.a : Lgz;
    //   874: invokevirtual b : ()V
    //   877: return
  }
  
  public void a_() {}
  
  public void a(int paramInt1, int paramInt2) {
    // Byte code:
    //   0: iconst_0
    //   1: istore_3
    //   2: iload_3
    //   3: aload_0
    //   4: getfield b : Ljava/util/Vector;
    //   7: invokevirtual size : ()I
    //   10: if_icmpge -> 73
    //   13: aload_0
    //   14: getfield b : Ljava/util/Vector;
    //   17: iload_3
    //   18: invokevirtual elementAt : (I)Ljava/lang/Object;
    //   21: checkcast ay
    //   24: dup
    //   25: astore #4
    //   27: ifnull -> 67
    //   30: aload #4
    //   32: getfield k : Z
    //   35: istore #5
    //   37: aload #4
    //   39: iload_1
    //   40: iload_2
    //   41: aload_0
    //   42: getfield g : I
    //   45: invokevirtual c : (III)Lay;
    //   48: pop
    //   49: iload #5
    //   51: ifne -> 67
    //   54: aload #4
    //   56: getfield k : Z
    //   59: ifeq -> 67
    //   62: aload_0
    //   63: iload_3
    //   64: putfield h : I
    //   67: iinc #3, 1
    //   70: goto -> 2
    //   73: return
  }
  
  public void b(int paramInt1, int paramInt2) {
    // Byte code:
    //   0: iconst_0
    //   1: istore_3
    //   2: iload_3
    //   3: aload_0
    //   4: getfield b : Ljava/util/Vector;
    //   7: invokevirtual size : ()I
    //   10: if_icmpge -> 48
    //   13: aload_0
    //   14: getfield b : Ljava/util/Vector;
    //   17: iload_3
    //   18: invokevirtual elementAt : (I)Ljava/lang/Object;
    //   21: checkcast ay
    //   24: dup
    //   25: astore #4
    //   27: ifnull -> 42
    //   30: aload #4
    //   32: iload_1
    //   33: iload_2
    //   34: aload_0
    //   35: getfield g : I
    //   38: invokevirtual a : (III)Lay;
    //   41: pop
    //   42: iinc #3, 1
    //   45: goto -> 2
    //   48: return
  }
  
  public void c(int paramInt1, int paramInt2) {
    // Byte code:
    //   0: iconst_0
    //   1: istore_3
    //   2: iconst_0
    //   3: istore #4
    //   5: iload #4
    //   7: aload_0
    //   8: getfield b : Ljava/util/Vector;
    //   11: invokevirtual size : ()I
    //   14: if_icmpge -> 74
    //   17: aload_0
    //   18: getfield b : Ljava/util/Vector;
    //   21: iload #4
    //   23: invokevirtual elementAt : (I)Ljava/lang/Object;
    //   26: checkcast ay
    //   29: dup
    //   30: astore #5
    //   32: ifnull -> 68
    //   35: aload #5
    //   37: iload_1
    //   38: iload_2
    //   39: aload_0
    //   40: getfield g : I
    //   43: invokevirtual b : (III)Lay;
    //   46: pop
    //   47: aload #5
    //   49: instanceof w
    //   52: ifeq -> 68
    //   55: aload #5
    //   57: checkcast w
    //   60: getfield k : Z
    //   63: ifeq -> 68
    //   66: iconst_1
    //   67: istore_3
    //   68: iinc #4, 1
    //   71: goto -> 5
    //   74: iload_3
    //   75: ifeq -> 79
    //   78: return
    //   79: getstatic gz.a : Lgz;
    //   82: getfield d : I
    //   85: getstatic gz.a : Lgz;
    //   88: getfield c : I
    //   91: isub
    //   92: istore #4
    //   94: aload_0
    //   95: dup
    //   96: getfield g : I
    //   99: iload #4
    //   101: iadd
    //   102: putfield g : I
    //   105: aload_0
    //   106: iload #4
    //   108: bipush #8
    //   110: ishl
    //   111: putfield a : I
    //   114: aload_0
    //   115: invokespecial e : ()V
    //   118: aload_0
    //   119: aload_0
    //   120: getfield g : I
    //   123: putfield f : I
    //   126: aload_0
    //   127: invokevirtual a_ : ()V
    //   130: return
  }
  
  public void a(int paramInt) {
    la la1 = this;
    switch (paramInt) {
      case 1:
        if (la1.b.size() > 1)
          la1.d(); 
      case 6:
        if (la1.b.size() > 1)
          la1.c(); 
      case 50:
        if (la1.b.size() > 1)
          la1.a(true); 
      case 56:
        if (la1.b.size() > 1)
          la1.a(false); 
      case 2:
        ay = la1.a();
        if (!gz.a.b() && ay != null && !(ay instanceof hv) && ((gz)gz.a).f > 0)
          gz.a.a(((gz)gz.a).f - 1); 
      case 5:
        ay = ay.a();
        if (!gz.a.b() && ay != null && !(ay instanceof hv) && ((gz)gz.a).f < 4)
          gz.a.a(((gz)gz.a).f + 1); 
      default:
        break;
    } 
    if (false)
      return; 
    ay ay;
    if ((ay = a()) != null)
      ay.a(paramInt); 
  }
  
  public void c(int paramInt) {
    ay ay;
    if ((ay = a()) != null)
      ay.c(paramInt); 
  }
  
  public void b(int paramInt) {
    la la1 = this;
    switch (paramInt) {
      case 1:
        if (la1.b.size() > 1)
          la1.d(); 
      case 6:
        if (la1.b.size() > 1)
          la1.c(); 
      case 50:
        if (la1.b.size() > 1)
          la1.a(true); 
      case 56:
        if (la1.b.size() > 1)
          la1.a(false); 
      default:
        break;
    } 
    if (false)
      return; 
    ay ay;
    if ((ay = a()) != null)
      ay.b(paramInt); 
  }
  
  private void c() {
    gz.a.a();
    ay ay;
    if ((ay = a()) != null && ay.e + (i << 1) > this.j && this.b != ay.e) {
      int i = ay.g + ay.e - this.j + i;
      this.g += this.j / 5;
      if (this.g >= i) {
        this.b = ay.e;
        this.g = i;
        return;
      } 
      this.b += this.j / 5;
      return;
    } 
    this.h++;
    h();
    i();
    f();
    h();
    j();
    i();
    a_();
  }
  
  private void d() {
    gz.a.a();
    ay ay;
    if ((ay = a()) != null && ay.e + (i << 1) > this.j && this.b) {
      int i = ay.g - i;
      this.g -= this.j / 5;
      if (this.g <= i) {
        this.b = false;
        this.g = i;
        return;
      } 
      this.b -= this.j / 5;
      return;
    } 
    this.h--;
    h();
    j();
    g();
    h();
    i();
    j();
    a_();
  }
  
  private void a(boolean paramBoolean) {
    // Byte code:
    //   0: getstatic gz.a : Lgz;
    //   3: invokevirtual a : ()V
    //   6: aload_0
    //   7: dup
    //   8: getfield g : I
    //   11: aload_0
    //   12: getfield j : I
    //   15: getstatic gz.a : Lgz;
    //   18: getfield a : Ljavax/microedition/lcdui/Font;
    //   21: invokevirtual getHeight : ()I
    //   24: isub
    //   25: iload_1
    //   26: ifeq -> 33
    //   29: iconst_m1
    //   30: goto -> 34
    //   33: iconst_1
    //   34: imul
    //   35: iadd
    //   36: putfield g : I
    //   39: aload_0
    //   40: invokespecial e : ()V
    //   43: aload_0
    //   44: dup
    //   45: astore_1
    //   46: invokevirtual a : ()Lay;
    //   49: dup
    //   50: astore_2
    //   51: ifnull -> 271
    //   54: aload_2
    //   55: getfield g : I
    //   58: aload_2
    //   59: getfield e : I
    //   62: iconst_2
    //   63: idiv
    //   64: iadd
    //   65: istore_2
    //   66: iconst_1
    //   67: istore_3
    //   68: aload_1
    //   69: getfield g : I
    //   72: iload_2
    //   73: if_icmpge -> 78
    //   76: iconst_m1
    //   77: istore_3
    //   78: ldc 2147483647
    //   80: istore_2
    //   81: iconst_m1
    //   82: istore #4
    //   84: aload_1
    //   85: getfield h : I
    //   88: istore #5
    //   90: iload #5
    //   92: iflt -> 259
    //   95: iload #5
    //   97: aload_1
    //   98: getfield b : Ljava/util/Vector;
    //   101: invokevirtual size : ()I
    //   104: if_icmpge -> 259
    //   107: aload_1
    //   108: getfield b : Ljava/util/Vector;
    //   111: iload #5
    //   113: invokevirtual elementAt : (I)Ljava/lang/Object;
    //   116: checkcast ay
    //   119: dup
    //   120: astore #6
    //   122: getfield r : Z
    //   125: ifne -> 250
    //   128: aload #6
    //   130: getfield g : I
    //   133: aload_1
    //   134: getfield g : I
    //   137: aload_1
    //   138: getfield j : I
    //   141: iconst_2
    //   142: idiv
    //   143: iadd
    //   144: if_icmpge -> 186
    //   147: aload #6
    //   149: getfield g : I
    //   152: aload #6
    //   154: getfield e : I
    //   157: iadd
    //   158: aload_1
    //   159: getfield g : I
    //   162: isub
    //   163: aload_1
    //   164: getfield g : I
    //   167: aload_1
    //   168: getfield j : I
    //   171: iconst_2
    //   172: idiv
    //   173: iadd
    //   174: if_icmple -> 186
    //   177: aload_1
    //   178: iload #5
    //   180: putfield h : I
    //   183: goto -> 259
    //   186: aload_1
    //   187: getfield g : I
    //   190: aload_1
    //   191: getfield j : I
    //   194: iconst_2
    //   195: idiv
    //   196: iadd
    //   197: aload #6
    //   199: getfield g : I
    //   202: aload #6
    //   204: getfield e : I
    //   207: iconst_2
    //   208: idiv
    //   209: iadd
    //   210: isub
    //   211: invokestatic abs : (I)I
    //   214: aload #6
    //   216: getfield e : I
    //   219: iconst_2
    //   220: idiv
    //   221: isub
    //   222: dup
    //   223: istore #6
    //   225: iload_2
    //   226: if_icmpge -> 239
    //   229: iload #6
    //   231: istore_2
    //   232: iload #5
    //   234: istore #4
    //   236: goto -> 250
    //   239: aload_1
    //   240: iload #5
    //   242: iload_3
    //   243: isub
    //   244: putfield h : I
    //   247: goto -> 259
    //   250: iload #5
    //   252: iload_3
    //   253: iadd
    //   254: istore #5
    //   256: goto -> 90
    //   259: iload #4
    //   261: iconst_m1
    //   262: if_icmpeq -> 271
    //   265: aload_1
    //   266: iload #4
    //   268: putfield h : I
    //   271: aload_0
    //   272: invokevirtual a_ : ()V
    //   275: return
  }
  
  public final ay a() {
    // Byte code:
    //   0: aload_0
    //   1: getfield b : Ljava/util/Vector;
    //   4: invokevirtual isEmpty : ()Z
    //   7: ifne -> 46
    //   10: aload_0
    //   11: getfield h : I
    //   14: iflt -> 46
    //   17: aload_0
    //   18: getfield h : I
    //   21: aload_0
    //   22: getfield b : Ljava/util/Vector;
    //   25: invokevirtual size : ()I
    //   28: if_icmpge -> 46
    //   31: aload_0
    //   32: getfield b : Ljava/util/Vector;
    //   35: aload_0
    //   36: getfield h : I
    //   39: invokevirtual elementAt : (I)Ljava/lang/Object;
    //   42: checkcast ay
    //   45: areturn
    //   46: aconst_null
    //   47: areturn
  }
  
  public final ar a() {
    ay ay;
    return ((ay = a()) != null && ay instanceof ar) ? (ar)ay : null;
  }
  
  final boolean a() {
    return (a() != null);
  }
  
  String b() {
    ay ay;
    return ((ay = a()) != null && ay.m) ? ay.e : null;
  }
  
  public final void c(String paramString) {
    this.c = paramString;
    this.d = null;
  }
  
  String a() {
    return (this.a == null) ? null : this.a.c;
  }
  
  void b_() {
    if (gz.a.b()) {
      gz.a.c();
      return;
    } 
    if (this.a != null)
      gz.a.a(this.a); 
  }
  
  public final la a(boolean paramBoolean) {
    this.b = paramBoolean;
    return this;
  }
  
  public final void d(int paramInt) {
    // Byte code:
    //   0: aload_0
    //   1: iload_1
    //   2: putfield h : I
    //   5: aload_0
    //   6: invokespecial h : ()V
    //   9: aload_0
    //   10: getfield b : Ljava/util/Vector;
    //   13: invokevirtual isEmpty : ()Z
    //   16: ifeq -> 20
    //   19: return
    //   20: aload_0
    //   21: getfield b : Ljava/util/Vector;
    //   24: iload_1
    //   25: invokevirtual elementAt : (I)Ljava/lang/Object;
    //   28: checkcast ay
    //   31: ifnonnull -> 35
    //   34: return
    //   35: aload_0
    //   36: invokespecial j : ()V
    //   39: aload_0
    //   40: invokespecial i : ()V
    //   43: aload_0
    //   44: invokespecial g : ()V
    //   47: aload_0
    //   48: invokespecial h : ()V
    //   51: getstatic gz.a : Lgz;
    //   54: invokevirtual b : ()V
    //   57: return
  }
  
  private void e() {
    if (this.j < this.e) {
      if (this.g < 0)
        this.g = 0; 
      int i = this.e - this.j;
      if (this.g > i)
        this.g = i; 
      return;
    } 
    this.g = 0;
  }
  
  private void f() {
    int i = this.h - 1;
    while (this.h < this.b.size()) {
      ay ay;
      if ((ay = a()) == null || !ay.r)
        return; 
      this.h++;
    } 
    if (this.h >= this.b.size())
      this.h = i; 
  }
  
  private void g() {
    int i = this.h + 1;
    while (this.h >= 0) {
      ay ay;
      if ((ay = a()) == null || !ay.r)
        return; 
      this.h--;
    } 
    if (this.h < 0)
      this.h = i; 
  }
  
  private void h() {
    // Byte code:
    //   0: aload_0
    //   1: getfield h : I
    //   4: aload_0
    //   5: getfield b : Ljava/util/Vector;
    //   8: invokevirtual size : ()I
    //   11: iconst_1
    //   12: isub
    //   13: if_icmple -> 51
    //   16: aload_0
    //   17: aload_0
    //   18: instanceof jr
    //   21: ifne -> 31
    //   24: aload_0
    //   25: instanceof ef
    //   28: ifeq -> 43
    //   31: aload_0
    //   32: getfield b : Ljava/util/Vector;
    //   35: invokevirtual size : ()I
    //   38: iconst_1
    //   39: isub
    //   40: goto -> 44
    //   43: iconst_0
    //   44: putfield h : I
    //   47: aload_0
    //   48: invokespecial f : ()V
    //   51: aload_0
    //   52: getfield h : I
    //   55: ifge -> 103
    //   58: aload_0
    //   59: aload_0
    //   60: instanceof jr
    //   63: ifne -> 83
    //   66: aload_0
    //   67: instanceof ef
    //   70: ifne -> 83
    //   73: aload_0
    //   74: getfield b : Ljava/util/Vector;
    //   77: invokevirtual isEmpty : ()Z
    //   80: ifeq -> 87
    //   83: iconst_0
    //   84: goto -> 96
    //   87: aload_0
    //   88: getfield b : Ljava/util/Vector;
    //   91: invokevirtual size : ()I
    //   94: iconst_1
    //   95: isub
    //   96: putfield h : I
    //   99: aload_0
    //   100: invokespecial g : ()V
    //   103: return
  }
  
  private void i() {
    // Byte code:
    //   0: aload_0
    //   1: getfield b : Ljava/util/Vector;
    //   4: aload_0
    //   5: getfield h : I
    //   8: invokevirtual elementAt : (I)Ljava/lang/Object;
    //   11: checkcast ay
    //   14: dup
    //   15: astore_1
    //   16: ifnonnull -> 20
    //   19: return
    //   20: aload_1
    //   21: getfield e : I
    //   24: getstatic la.i : I
    //   27: iconst_1
    //   28: ishl
    //   29: iadd
    //   30: aload_0
    //   31: getfield j : I
    //   34: if_icmple -> 41
    //   37: iconst_1
    //   38: goto -> 42
    //   41: iconst_0
    //   42: ifne -> 103
    //   45: aload_1
    //   46: getfield g : I
    //   49: aload_0
    //   50: getfield g : I
    //   53: isub
    //   54: aload_1
    //   55: getfield e : I
    //   58: iadd
    //   59: getstatic la.i : I
    //   62: iadd
    //   63: aload_0
    //   64: getfield j : I
    //   67: if_icmplt -> 148
    //   70: aload_0
    //   71: aload_1
    //   72: getfield g : I
    //   75: aload_1
    //   76: getfield e : I
    //   79: iadd
    //   80: aload_0
    //   81: getfield j : I
    //   84: isub
    //   85: getstatic la.i : I
    //   88: iadd
    //   89: putfield g : I
    //   92: aload_0
    //   93: aload_1
    //   94: getfield e : I
    //   97: putfield b : I
    //   100: goto -> 148
    //   103: aload_1
    //   104: getfield g : I
    //   107: aload_1
    //   108: getfield e : I
    //   111: iadd
    //   112: aload_0
    //   113: getfield g : I
    //   116: isub
    //   117: aload_0
    //   118: getfield j : I
    //   121: if_icmplt -> 148
    //   124: aload_0
    //   125: aload_1
    //   126: getfield g : I
    //   129: getstatic la.i : I
    //   132: isub
    //   133: putfield g : I
    //   136: aload_0
    //   137: aload_0
    //   138: getfield j : I
    //   141: getstatic la.i : I
    //   144: isub
    //   145: putfield b : I
    //   148: getstatic gz.a : Lgz;
    //   151: invokevirtual b : ()V
    //   154: return
  }
  
  private void j() {
    // Byte code:
    //   0: aload_0
    //   1: getfield b : Ljava/util/Vector;
    //   4: aload_0
    //   5: getfield h : I
    //   8: invokevirtual elementAt : (I)Ljava/lang/Object;
    //   11: checkcast ay
    //   14: dup
    //   15: astore_1
    //   16: ifnonnull -> 20
    //   19: return
    //   20: aload_1
    //   21: getfield e : I
    //   24: getstatic la.i : I
    //   27: iconst_1
    //   28: ishl
    //   29: iadd
    //   30: aload_0
    //   31: getfield j : I
    //   34: if_icmple -> 41
    //   37: iconst_1
    //   38: goto -> 42
    //   41: iconst_0
    //   42: ifne -> 81
    //   45: aload_1
    //   46: getfield g : I
    //   49: aload_0
    //   50: getfield g : I
    //   53: isub
    //   54: getstatic la.i : I
    //   57: isub
    //   58: ifgt -> 142
    //   61: aload_0
    //   62: aload_1
    //   63: getfield g : I
    //   66: getstatic la.i : I
    //   69: isub
    //   70: putfield g : I
    //   73: aload_0
    //   74: iconst_0
    //   75: putfield b : I
    //   78: goto -> 142
    //   81: aload_1
    //   82: getfield g : I
    //   85: aload_1
    //   86: getfield e : I
    //   89: iadd
    //   90: aload_0
    //   91: getfield j : I
    //   94: isub
    //   95: aload_0
    //   96: getfield g : I
    //   99: isub
    //   100: ifgt -> 142
    //   103: aload_0
    //   104: aload_1
    //   105: getfield g : I
    //   108: aload_1
    //   109: getfield e : I
    //   112: iadd
    //   113: aload_0
    //   114: getfield j : I
    //   117: isub
    //   118: getstatic la.i : I
    //   121: iadd
    //   122: putfield g : I
    //   125: aload_0
    //   126: aload_1
    //   127: getfield e : I
    //   130: aload_0
    //   131: getfield j : I
    //   134: isub
    //   135: getstatic la.i : I
    //   138: iadd
    //   139: putfield b : I
    //   142: getstatic gz.a : Lgz;
    //   145: invokevirtual b : ()V
    //   148: return
  }
  
  static {
    Image.createImage(1, 1);
  }
}


/* Location:              /home/kost/Загрузки/latest.jar!/la.class
 * Java compiler version: 4 (48.0)
 * JD-Core Version:       1.1.3
 */